Workbook

Sheet Menu
A1: Menu du 1er au 21 octobre 2026 — Nicolas et Aurélie
A2: Une ligne par aliment. Poids crus (viandes, poissons, légumes, pommes de terre) ou secs (riz, pâtes) ; lentilles égouttées ; huile = cuisson + assaisonnement. Les quantités en bleu se modifient ici : Nutrition, Courses, listes individuelles et Budget se recalculent.
A3: Légende : orange = repas plaisir · bleu = repas poisson · case vide = aliment non prévu pour cette personne
A5: Repas | B5: Plat | C5: Aliment | D5: Nicolas | E5: Aurélie | F5: Unité
A6: Jeudi 1 octobre — course 1 (du 1er au 5)
A7: Petit-déjeuner | B7: Smoothie + œuf (Nicolas) / œufs, jambon, pain, pomme (Aurélie) | C7: Lait | D7: 250 | F7: ml
C8: Bananes | D8: 100 | F8: g
C9: Flocons d'avoine | D9: 65 | F9: g
C10: Œufs | D10: 1 | E10: 2 | F10: unité(s)
C11: Jambon | E11: 30 | F11: g
C12: Tomates | E12: 80 | F12: g
C13: Pain complet | E13: 40 | F13: g
C14: Pommes | E14: 150 | F14: g
A15: Déjeuner | B15: Poulet rôti, pommes de terre, haricots verts | C15: Poulet | D15: 150 | E15: 120 | F15: g
C16: Pommes de terre | D16: 360 | E16: 170 | F16: g
C17: Haricots verts | D17: 250 | E17: 280 | F17: g
C18: Huile | D18: 10 | E18: 7 | F18: g
A19: Dîner | B19: Poisson blanc, patate douce, poêlée courgettes-poivrons | C19: Poisson blanc | D19: 150 | E19: 125 | F19: g
C20: Patates douces | D20: 300 | E20: 140 | F20: g
C21: Courgettes | D21: 170 | E21: 200 | F21: g
C22: Poivrons | D22: 50 | E22: 60 | F22: g
C23: Oignons | D23: 20 | E23: 20 | F23: g
C24: Huile | D24: 10 | E24: 7 | F24: g
A25: Dessert | B25: Yaourt + chocolat | C25: Yaourt nature | D25: 125 | E25: 125 | F25: g
C26: Chocolat noir | D26: 10 | E26: 10 | F26: g
A28: Vendredi 2 octobre
A29: Petit-déjeuner | B29: Smoothie + œuf (Nicolas) / œufs, jambon, pain, pomme (Aurélie) | C29: Lait | D29: 250 | F29: ml
C30: Bananes | D30: 100 | F30: g
C31: Flocons d'avoine | D31: 65 | F31: g
C32: Œufs | D32: 1 | E32: 2 | F32: unité(s)
C33: Jambon | E33: 30 | F33: g
C34: Tomates | E34: 80 | F34: g
C35: Pain complet | E35: 40 | F35: g
C36: Pommes | E36: 150 | F36: g
A37: Déjeuner | B37: Carry poulet-lentilles, riz, carottes râpées | C37: Poulet | D37: 100 | E37: 80 | F37: g
C38: Lentilles (égouttées) | D38: 140 | E38: 120 | F38: g
C39: Riz (sec) | D39: 50 | E39: 20 | F39: g
C40: Tomates | D40: 120 | E40: 150 | F40: g
C41: Oignons | D41: 40 | E41: 40 | F41: g
C42: Carottes | D42: 80 | E42: 100 | F42: g
C43: Huile | D43: 10 | E43: 7 | F43: g
A44: Dîner | B44: Omelette paysanne (pommes de terre, courgettes) + salade-tomate | C44: Œufs | D44: 3 | E44: 2 | F44: unité(s)
C45: Pommes de terre | D45: 300 | E45: 110 | F45: g
C46: Courgettes | D46: 150 | E46: 170 | F46: g
C47: Tomates | D47: 100 | E47: 130 | F47: g
C48: Salade | D48: 40 | E48: 60 | F48: g
C49: Oignons | D49: 20 | E49: 20 | F49: g
C50: Huile | D50: 8 | E50: 6 | F50: g
A51: Dessert | B51: Ananas | C51: Ananas | D51: 110 | E51: 90 | F51: g
A53: Samedi 3 octobre
A54: Petit-déjeuner | B54: Smoothie + œuf (Nicolas) / œufs, jambon, pain, pomme (Aurélie) | C54: Lait | D54: 250 | F54: ml
C55: Bananes | D55: 100 | F55: g
C56: Flocons d'avoine | D56: 65 | F56: g
C57: Œufs | D57: 1 | E57: 2 | F57: unité(s)
C58: Jambon | E58: 30 | F58: g
C59: Tomates | E59: 80 | F59: g
C60: Pain complet | E60: 40 | F60: g
C61: Pommes | E61: 150 | F61: g
A62: Déjeuner | B62: Salade tiède lentilles, œufs durs, pommes de terre, tomates | C62: Lentilles (égouttées) | D62: 150 | E62: 120 | F62: g
C63: Œufs | D63: 2 | E63: 2 | F63: unité(s)
C64: Pommes de terre | D64: 240 | E64: 90 | F64: g
C65: Tomates | D65: 150 | E65: 180 | F65: g
C66: Oignons | D66: 30 | E66: 30 | F66: g
C67: Huile | D67: 10 | E67: 7 | F67: g
A68: Dîner | B68: Bœuf sauté asiatique, riz, poivrons-carottes | C68: Bœuf | D68: 130 | E68: 100 | F68: g
C69: Riz (sec) | D69: 85 | E69: 45 | F69: g
C70: Poivrons | D70: 60 | E70: 80 | F70: g
C71: Carottes | D71: 80 | E71: 100 | F71: g
C72: Oignons | D72: 30 | E72: 30 | F72: g
C73: Huile | D73: 10 | E73: 7 | F73: g
A74: Dessert | B74: Ananas | C74: Ananas | D74: 110 | E74: 90 | F74: g
A76: Dimanche 4 octobre — repas plaisir
A77: Petit-déjeuner | B77: Smoothie + œuf (Nicolas) / œufs, jambon, pain, pomme (Aurélie) | C77: Lait | D77: 250 | F77: ml
C78: Bananes | D78: 100 | F78: g
C79: Flocons d'avoine | D79: 65 | F79: g
C80: Œufs | D80: 1 | E80: 2 | F80: unité(s)
C81: Jambon | E81: 30 | F81: g
C82: Tomates | E82: 80 | F82: g
C83: Pain complet | E83: 40 | F83: g
C84: Pommes | E84: 150 | F84: g
A85: Déjeuner | B85: Burger maison, potatoes au four, crudités | C85: Bœuf | D85: 150 | E85: 120 | F85: g
C86: Pains burger | D86: 1 | E86: 1 | F86: unité(s)
C87: Cheddar | D87: 20 | E87: 15 | F87: g
C88: Tomates | D88: 60 | E88: 80 | F88: g
C89: Salade | D89: 30 | E89: 40 | F89: g
C90: Oignons | D90: 20 | E90: 20 | F90: g
C91: Pommes de terre | D91: 300 | E91: 140 | F91: g
C92: Huile | D92: 8 | E92: 5 | F92: g
A93: Dîner | B93: Salade poulet, avocat, tomate, maïs | C93: Poulet | D93: 130 | E93: 100 | F93: g
C94: Avocat (chair) | D94: 80 | E94: 60 | F94: g
C95: Tomates | D95: 120 | E95: 150 | F95: g
C96: Maïs | D96: 40 | E96: 30 | F96: g
C97: Salade | D97: 40 | E97: 60 | F97: g
C98: Huile | D98: 8 | E98: 6 | F98: g
A99: Dessert | B99: Glace | C99: Glace | D99: 75 | E99: 55 | F99: g
A101: Lundi 5 octobre
A102: Petit-déjeuner | B102: Smoothie + œuf (Nicolas) / œufs, jambon, pain, pomme (Aurélie) | C102: Lait | D102: 250 | F102: ml
C103: Bananes | D103: 100 | F103: g
C104: Flocons d'avoine | D104: 65 | F104: g
C105: Œufs | D105: 1 | E105: 2 | F105: unité(s)
...

Sheet Budget
A1: Budget individuel du 1er au 21 octobre
A2: Chacun paie ce qu'il consomme au prix du gramme, du ml ou de l'unité. Les restes (paquets entamés, surgelés) repartent en stock sur le cycle suivant. Nicolas + Aurélie + reste en stock = dépense totale.
B4: Nicolas | C4: Aurélie | D4: Reste en stock (reporté) | E4: Total
A5: Coût sur 21 jours (€) | B5: =Courses!T54 -> 176.91886 | C5: =Courses!U54 -> 167.84261 | D5: =Courses!W54 -> 18.349558 | E5: =Courses!M57 -> 363.11103
A6: Part du total | B6: =B5/$E$5 -> 0.48723075 | C6: =C5/$E$5 -> 0.46223496 | D6: =D5/$E$5 -> 0.050534291 | E6: =E5/$E$5 -> 1
A7: Par jour (€) | B7: =B5/21 -> 8.4247076 | C7: =C5/21 -> 7.9925053 | E7: =E5/21 -> 17.291001
A8: Par repas (€, 3 repas/jour) | B8: =B5/63 -> 2.8082359 | C8: =C5/63 -> 2.6641684 | E8: =E5/126 -> 2.8818336
A9: Contrôle (doit faire 0) | E9: =E5-B5-C5-D5 -> 7.1054274e-14
A11: Par course
B12: Consommation Nicolas | C12: Consommation Aurélie | D12: Dépense en magasin
A13: Course 1 — 01/10 (du 1er au 5) | B13: =Courses!M55 -> 42.986312 | C13: =Courses!M56 -> 40.369641 | D13: =Courses!M54 -> 129.9301
A14: Course 2 — 06/10 (du 6 au 21) | B14: =Courses!Q55 -> 133.93255 | C14: =Courses!Q56 -> 127.47297 | D14: =Courses!Q54 -> 233.18093
A16: Course 1 : au plus juste pour 5 jours. Les conditionnements entamés (paquet de poulet, riz, avoine…) passent sur la course 2, ce qui explique une dépense de course 1 supérieure à la consommation des 5 jours.

Sheet Courses
A1: Liste de courses — Nicolas et Aurélie (1er au 21 octobre)
A2: Course 1 le 01/10 : uniquement ce qu'il faut du 1er au 5 inclus. Course 2 le 06/10 : tout ce qu'il faut du 6 au 21, restes de la course 1 déduits. Une ligne par produit, besoins de Nicolas et d'Aurélie séparés. À acheter = nombre de conditionnements, ou grammes si vrac. Jaune = modifiable. Case vide = rien à acheter ou pas de besoin.
A4: Produit | J4: Course 1 — jeudi 01/10 (du 1er au 5) | N4: Course 2 — mardi 06/10 (du 6 au 21) | R4: Total 21 jours | Y4: Calculs
A5: Catégorie | B5: Aliment | C5: Unité | D5: Achat par | E5: Conditionnement | F5: Vrac (1 = oui) | G5: Rendement | H5: Prix (€ par achat, ou €/kg si vrac) | I5: Stock déjà là | J5: Besoin Nicolas | K5: Besoin Aurélie | L5: À acheter | M5: Dépense (€) | N5: Besoin Nicolas | O5: Besoin Aurélie | P5: À acheter | Q5: Dépense (€) | R5: Besoin Nicolas | S5: Besoin Aurélie | T5: Coût Nicolas (€) | U5: Coût Aurélie (€) | V5: Reste après le 21 | W5: Valeur du reste (€) | X5: Conservation / commentaire | Y5: Prix par g, ml ou unité (€) | Z5: Reste après la course 1
A6: Viande | B6: Poulet | C6: g | D6: paquet 1 kg | E6: 1000 | F6: 0 | G6: 1 | H6: 11.27 | I6: 0 | J6: =SUMIFS(Détail!$F$2:$F$929,Détail!$E$2:$E$929,$B6,Détail!$D$2:$D$929,"Nicolas",Détail!$J$2:$J$929,1) -> 660 | K6: =SUMIFS(Détail!$F$2:$F$929,Détail!$E$2:$E$929,$B6,Détail!$D$2:$D$929,"Aurélie",Détail!$J$2:$J$929,1) -> 520 | L6: =IF(J6+K6-I6<=0,0,IF(F6=1,(J6+K6-I6)/G6,ROUNDUP((J6+K6-I6)/E6,0))) -> 2 | M6: =IF(H6="",0,IF(F6=1,L6/1000*H6,L6*H6)) -> 22.54 | N6: =SUMIFS(Détail!$F$2:$F$929,Détail!$E$2:$E$929,$B6,Détail!$D$2:$D$929,"Nicolas",Détail!$J$2:$J$929,2) -> 2110 | O6: =SUMIFS(Détail!$F$2:$F$929,Détail!$E$2:$E$929,$B6,Détail!$D$2:$D$929,"Aurélie",Détail!$J$2:$J$929,2) -> 1670 | P6: =IF(N6+O6-Z6<=0,0,IF(F6=1,(N6+O6-Z6)/G6,ROUNDUP((N6+O6-Z6)/E6,0))) -> 3 | Q6: =IF(H6="",0,IF(F6=1,P6/1000*H6,P6*H6)) -> 33.81 | R6: =J6+N6 -> 2770 | S6: =K6+O6 -> 2190 | T6: =R6*Y6 -> 31.2179 | U6: =S6*Y6 -> 24.6813 | V6: =Z6+IF(F6=1,P6*G6,P6*E6)-(N6+O6) -> 40 | W6: =V6*Y6 -> 0.4508 | X6: Congeler en portions d'un repas le jour de l'achat. | Y6: =IF(H6="",0,IF(F6=1,H6/1000/G6,H6/E6)) -> 0.01127 | Z6: =I6+IF(F6=1,L6*G6,L6*E6)-(J6+K6) -> 820
A7: Viande | B7: Bœuf | C7: g | D7: paquet 900 g | E7: 900 | F7: 0 | G7: 1 | H7: 8.4 | I7: 0 | J7: =SUMIFS(Détail!$F$2:$F$929,Détail!$E$2:$E$929,$B7,Détail!$D$2:$D$929,"Nicolas",Détail!$J$2:$J$929,1) -> 280 | K7: =SUMIFS(Détail!$F$2:$F$929,Détail!$E$2:$E$929,$B7,Détail!$D$2:$D$929,"Aurélie",Détail!$J$2:$J$929,1) -> 220 | L7: =IF(J7+K7-I7<=0,0,IF(F7=1,(J7+K7-I7)/G7,ROUNDUP((J7+K7-I7)/E7,0))) -> 1 | M7: =IF(H7="",0,IF(F7=1,L7/1000*H7,L7*H7)) -> 8.4 | N7: =SUMIFS(Détail!$F$2:$F$929,Détail!$E$2:$E$929,$B7,Détail!$D$2:$D$929,"Nicolas",Détail!$J$2:$J$929,2) -> 660 | O7: =SUMIFS(Détail!$F$2:$F$929,Détail!$E$2:$E$929,$B7,Détail!$D$2:$D$929,"Aurélie",Détail!$J$2:$J$929,2) -> 515 | P7: =IF(N7+O7-Z7<=0,0,IF(F7=1,(N7+O7-Z7)/G7,ROUNDUP((N7+O7-Z7)/E7,0))) -> 1 | Q7: =IF(H7="",0,IF(F7=1,P7/1000*H7,P7*H7)) -> 8.4 | R7: =J7+N7 -> 940 | S7: =K7+O7 -> 735 | T7: =R7*Y7 -> 8.7733333 | U7: =S7*Y7 -> 6.86 | V7: =Z7+IF(F7=1,P7*G7,P7*E7)-(N7+O7) -> 125 | W7: =V7*Y7 -> 1.1666667 | X7: Congeler en portions. | Y7: =IF(H7="",0,IF(F7=1,H7/1000/G7,H7/E7)) -> 0.0093333333 | Z7: =I7+IF(F7=1,L7*G7,L7*E7)-(J7+K7) -> 400
A8: Viande | B8: Lardons | C8: g | D8: paquet 200 g | E8: 200 | F8: 0 | G8: 1 | H8: 1.27 | I8: 0 | J8: =SUMIFS(Détail!$F$2:$F$929,Détail!$E$2:$E$929,$B8,Détail!$D$2:$D$929,"Nicolas",Détail!$J$2:$J$929,1) -> 0 | K8: =SUMIFS(Détail!$F$2:$F$929,Détail!$E$2:$E$929,$B8,Détail!$D$2:$D$929,"Aurélie",Détail!$J$2:$J$929,1) -> 0 | L8: =IF(J8+K8-I8<=0,0,IF(F8=1,(J8+K8-I8)/G8,ROUNDUP((J8+K8-I8)/E8,0))) -> 0 | M8: =IF(H8="",0,IF(F8=1,L8/1000*H8,L8*H8)) -> 0 | N8: =SUMIFS(Détail!$F$2:$F$929,Détail!$E$2:$E$929,$B8,Détail!$D$2:$D$929,"Nicolas",Détail!$J$2:$J$929,2) -> 120 | O8: =SUMIFS(Détail!$F$2:$F$929,Détail!$E$2:$E$929,$B8,Détail!$D$2:$D$929,"Aurélie",Détail!$J$2:$J$929,2) -> 80 | P8: =IF(N8+O8-Z8<=0,0,IF(F8=1,(N8+O8-Z8)/G8,ROUNDUP((N8+O8-Z8)/E8,0))) -> 1 | Q8: =IF(H8="",0,IF(F8=1,P8/1000*H8,P8*H8)) -> 1.27 | R8: =J8+N8 -> 120 | S8: =K8+O8 -> 80 | T8: =R8*Y8 -> 0.762 | U8: =S8*Y8 -> 0.508 | V8: =Z8+IF(F8=1,P8*G8,P8*E8)-(N8+O8) -> 0 | W8: =V8*Y8 -> 0 | X8: Longue DLC sous vide, se congèle. | Y8: =IF(H8="",0,IF(F8=1,H8/1000/G8,H8/E8)) -> 0.00635 | Z8: =I8+IF(F8=1,L8*G8,L8*E8)-(J8+K8) -> 0
A9: Viande | B9: Jambon | C9: g | D9: paquet 500 g (hypothèse) | E9: 500 | F9: 0 | G9: 1 | H9: 5.62 | I9: 0 | J9: =SUMIFS(Détail!$F$2:$F$929,Détail!$E$2:$E$929,$B9,Détail!$D$2:$D$929,"Nicolas",Détail!$J$2:$J$929,1) -> 0 | K9: =SUMIFS(Détail!$F$2:$F$929,Détail!$E$2:$E$929,$B9,Détail!$D$2:$D$929,"Aurélie",Détail!$J$2:$J$929,1) -> 150 | L9: =IF(J9+K9-I9<=0,0,IF(F9=1,(J9+K9-I9)/G9,ROUNDUP((J9+K9-I9)/E9,0))) -> 1 | M9: =IF(H9="",0,IF(F9=1,L9/1000*H9,L9*H9)) -> 5.62 | N9: =SUMIFS(Détail!$F$2:$F$929,Détail!$E$2:$E$929,$B9,Détail!$D$2:$D$929,"Nicolas",Détail!$J$2:$J$929,2) -> 40 | O9: =SUMIFS(Détail!$F$2:$F$929,Détail!$E$2:$E$929,$B9,Détail!$D$2:$D$929,"Aurélie",Détail!$J$2:$J$929,2) -> 510 | P9: =IF(N9+O9-Z9<=0,0,IF(F9=1,(N9+O9-Z9)/G9,ROUNDUP((N9+O9-Z9)/E9,0))) -> 1 | Q9: =IF(H9="",0,IF(F9=1,P9/1000*H9,P9*H9)) -> 5.62 | R9: =J9+N9 -> 40 | S9: =K9+O9 -> 660 | T9: =R9*Y9 -> 0.4496 | U9: =S9*Y9 -> 7.4184 | V9: =Z9+IF(F9=1,P9*G9,P9*E9)-(N9+O9) -> 300 | W9: =V9*Y9 -> 3.372 | X9: 2 à 3 jours une fois ouvert : préférer plusieurs petits paquets. | Y9: =IF(H9="",0,IF(F9=1,H9/1000/G9,H9/E9)) -> 0.01124 | Z9: =I9+IF(F9=1,L9*G9,L9*E9)-(J9+K9) -> 350
A10: Poisson | B10: Poisson blanc | C10: g | D10: sachet 1 kg surgelé | E10: 1000 | F10: 0 | G10: 1 | H10: 7.49 | I10: 0 | J10: =SUMIFS(Détail!$F$2:$F$929,Détail!$E$2:$E$929,$B10,Détail!$D$2:$D$929,"Nicolas",Détail!$J$2:$J$929,1) -> 150 | K10: =SUMIFS(Détail!$F$2:$F$929,Détail!$E$2:$E$929,$B10,Détail!$D$2:$D$929,"Aurélie",Détail!$J$2:$J$929,1) -> 125 | L10: =IF(J10+K10-I10<=0,0,IF(F10=1,(J10+K10-I10)/G10,ROUNDUP((J10+K10-I10)/E10,0))) -> 1 | M10: =IF(H10="",0,IF(F10=1,L10/1000*H10,L10*H10)) -> 7.49 | N10: =SUMIFS(Détail!$F$2:$F$929,Détail!$E$2:$E$929,$B10,Détail!$D$2:$D$929,"Nicolas",Détail!$J$2:$J$929,2) -> 900 | O10: =SUMIFS(Détail!$F$2:$F$929,Détail!$E$2:$E$929,$B10,Détail!$D$2:$D$929,"Aurélie",Détail!$J$2:$J$929,2) -> 750 | P10: =IF(N10+O10-Z10<=0,0,IF(F10=1,(N10+O10-Z10)/G10,ROUNDUP((N10+O10-Z10)/E10,0))) -> 1 | Q10: =IF(H10="",0,IF(F10=1,P10/1000*H10,P10*H10)) -> 7.49 | R10: =J10+N10 -> 1050 | S10: =K10+O10 -> 875 | T10: =R10*Y10 -> 7.8645 | U10: =S10*Y10 -> 6.55375 | V10: =Z10+IF(F10=1,P10*G10,P10*E10)-(N10+O10) -> 75 | W10: =V10*Y10 -> 0.56175 | X10: Surgelé. | Y10: =IF(H10="",0,IF(F10=1,H10/1000/G10,H10/E10)) -> 0.00749 | Z10: =I10+IF(F10=1,L10*G10,L10*E10)-(J10+K10) -> 725
A11: Œufs et laitages | B11: Œufs | C11: unité | D11: boîte de 12 | E11: 12 | F11: 0 | G11: 1 | H11: 3.8 | I11: 0 | J11: =SUMIFS(Détail!$F$2:$F$929,Détail!$E$2:$E$929,$B11,Détail!$D$2:$D$929,"Nicolas",Détail!$J$2:$J$929,1) -> 10 | K11: =SUMIFS(Détail!$F$2:$F$929,Détail!$E$2:$E$929,$B11,Détail!$D$2:$D$929,"Aurélie",Détail!$J$2:$J$929,1) -> 14 | L11: =IF(J11+K11-I11<=0,0,IF(F11=1,(J11+K11-I11)/G11,ROUNDUP((J11+K11-I11)/E11,0))) -> 2 | M11: =IF(H11="",0,IF(F11=1,L11/1000*H11,L11*H11)) -> 7.6 | N11: =SUMIFS(Détail!$F$2:$F$929,Détail!$E$2:$E$929,$B11,Détail!$D$2:$D$929,"Nicolas",Détail!$J$2:$J$929,2) -> 26 | O11: =SUMIFS(Détail!$F$2:$F$929,Détail!$E$2:$E$929,$B11,Détail!$D$2:$D$929,"Aurélie",Détail!$J$2:$J$929,2) -> 41 | P11: =IF(N11+O11-Z11<=0,0,IF(F11=1,(N11+O11-Z11)/G11,ROUNDUP((N11+O11-Z11)/E11,0))) -> 6 | Q11: =IF(H11="",0,IF(F11=1,P11/1000*H11,P11*H11)) -> 22.8 | R11: =J11+N11 -> 36 | S11: =K11+O11 -> 55 | T11: =R11*Y11 -> 11.4 | U11: =S11*Y11 -> 17.416667 | V11: =Z11+IF(F11=1,P11*G11,P11*E11)-(N11+O11) -> 5 | W11: =V11*Y11 -> 1.5833333 | X11: Vérifier une date au-delà du 21/10. | Y11: =IF(H11="",0,IF(F11=1,H11/1000/G11,H11/E11)) -> 0.31666667 | Z11: =I11+IF(F11=1,L11*G11,L11*E11)-(J11+K11) -> 0
A12: Œufs et laitages | B12: Lait | C12: ml | D12: brique 1 L | E12: 1000 | F12: 0 | G12: 1 | H12: 1.19 | I12: 0 | J12: =SUMIFS(Détail!$F$2:$F$929,Détail!$E$2:$E$929,$B12,Détail!$D$2:$D$929,"Nicolas",Détail!$J$2:$J$929,1) -> 1250 | K12: =SUMIFS(Détail!$F$2:$F$929,Détail!$E$2:$E$929,$B12,Détail!$D$2:$D$929,"Aurélie",Détail!$J$2:$J$929,1) -> 0 | L12: =IF(J12+K12-I12<=0,0,IF(F12=1,(J12+K12-I12)/G12,ROUNDUP((J12+K12-I12)/E12,0))) -> 2 | M12: =IF(H12="",0,IF(F12=1,L12/1000*H12,L12*H12)) -> 2.38 | N12: =SUMIFS(Détail!$F$2:$F$929,Détail!$E$2:$E$929,$B12,Détail!$D$2:$D$929,"Nicolas",Détail!$J$2:$J$929,2) -> 4260 | O12: =SUMIFS(Détail!$F$2:$F$929,Détail!$E$2:$E$929,$B12,Détail!$D$2:$D$929,"Aurélie",Détail!$J$2:$J$929,2) -> 220 | P12: =IF(N12+O12-Z12<=0,0,IF(F12=1,(N12+O12-Z12)/G12,ROUNDUP((N12+O12-Z12)/E12,0))) -> 4 | Q12: =IF(H12="",0,IF(F12=1,P12/1000*H12,P12*H12)) -> 4.76 | R12: =J12+N12 -> 5510 | S12: =K12+O12 -> 220 | T12: =R12*Y12 -> 6.5569 | U12: =S12*Y12 -> 0.2618 | V12: =Z12+IF(F12=1,P12*G12,P12*E12)-(N12+O12) -> 270 | W12: =V12*Y12 -> 0.3213 | X12: UHT : se garde des mois fermé. | Y12: =IF(H12="",0,IF(F12=1,H12/1000/G12,H12/E12)) -> 0.00119 | Z12: =I12+IF(F12=1,L12*G12,L12*E12)-(J12+K12) -> 750
A13: Œufs et laitages | B13: Yaourt nature | C13: g | D13: pot 500 g | E13: 500 | F13: 0 | G13: 1 | H13: 3.25 | I13: 0 | J13: =SUMIFS(Détail!$F$2:$F$929,Détail!$E$2:$E$929,$B13,Détail!$D$2:$D$929,"Nicolas",Détail!$J$2:$J$929,1) -> 250 | K13: =SUMIFS(Détail!$F$2:$F$929,Détail!$E$2:$E$929,$B13,Détail!$D$2:$D$929,"Aurélie",Détail!$J$2:$J$929,1) -> 250 | L13: =IF(J13+K13-I13<=0,0,IF(F13=1,(J13+K13-I13)/G13,ROUNDUP((J13+K13-I13)/E13,0))) -> 1 | M13: =IF(H13="",0,IF(F13=1,L13/1000*H13,L13*H13)) -> 3.25 | N13: =SUMIFS(Détail!$F$2:$F$929,Détail!$E$2:$E$929,$B13,Détail!$D$2:$D$929,"Nicolas",Détail!$J$2:$J$929,2) -> 750 | O13: =SUMIFS(Détail!$F$2:$F$929,Détail!$E$2:$E$929,$B13,Détail!$D$2:$D$929,"Aurélie",Détail!$J$2:$J$929,2) -> 750 | P13: =IF(N13+O13-Z13<=0,0,IF(F13=1,(N13+O13-Z13)/G13,ROUNDUP((N13+O13-Z13)/E13,0))) -> 3 | Q13: =IF(H13="",0,IF(F13=1,P13/1000*H13,P13*H13)) -> 9.75 | R13: =J13+N13 -> 1000 | S13: =K13+O13 -> 1000 | T13: =R13*Y13 -> 6.5 | U13: =S13*Y13 -> 6.5 | V13: =Z13+IF(F13=1,P13*G13,P13*E13)-(N13+O13) -> 0 | W13: =V13*Y13 -> 0 | X13: Vérifier une date au-delà du 21/10. | Y13: =IF(H13="",0,IF(F13=1,H13/1000/G13,H13/E13)) -> 0.0065 | Z13: =I13+IF(F13=1,L13*G13,L13*E13)-(J13+K13) -> 0
A14: Œufs et laitages | B14: Mozzarella râpée | C14: g | D14: sachet 150 g | E14: 150 | F14: 0 | G14: 1 | H14: 3.13 | I14: 0 | J14: =SUMIFS(Détail!$F$2:$F$929,Détail!$E$2:$E$929,$B14,Détail!$D$2:$D$929,"Nicolas",Détail!$J$2:$J$929,1) -> 0 | K14: =SUMIFS(Détail!$F$2:$F$929,Détail!$E$2:$E$929,$B14,Détail!$D$2:$D$929,"Aurélie",Détail!$J$2:$J$929,1) -> 0 | L14: =IF(J14+K14-I14<=0,0,IF(F14=1,(J14+K14-I14)/G14,ROUNDUP((J14+K14-I14)/E14,0))) -> 0 | M14: =IF(H14="",0,IF(F14=1,L14/1000*H14,L14*H14)) -> 0 | N14: =SUMIFS(Détail!$F$2:$F$929,Détail!$E$2:$E$929,$B14,Détail!$D$2:$D$929,"Nicolas",Détail!$J$2:$J$929,2) -> 110 | O14: =SUMIFS(Détail!$F$2:$F$929,Détail!$E$2:$E$929,$B14,Détail!$D$2:$D$929,"Aurélie",Détail!$J$2:$J$929,2) -> 85 | P14: =IF(N14+O14-Z14<=0,0,IF(F14=1,(N14+O14-Z14)/G14,ROUNDUP((N14+O14-Z14)/E14,0))) -> 2 | Q14: =IF(H14="",0,IF(F14=1,P14/1000*H14,P14*H14)) -> 6.26 | R14: =J14+N14 -> 110 | S14: =K14+O14 -> 85 | T14: =R14*Y14 -> 2.2953333 | U14: =S14*Y14 -> 1.7736667 | V14: =Z14+IF(F14=1,P14*G14,P14*E14)-(N14+O14) -> 105 | W14: =V14*Y14 -> 2.191 | X14: Se congèle. | Y14: =IF(H14="",0,IF(F14=1,H14/1000/G14,H14/E14)) -> 0.020866667 | Z14: =I14+IF(F14=1,L14*G14,L14*E14)-(J14+K14) -> 0
A15: Œufs et laitages | B15: Cheddar | C15: g | D15: vrac (g) | E15: 1 | F15: 1 | G15: 1 | H15: 16.5 | I15: 0 | J15: =SUMIFS(Détail!$F$2:$F$929,Détail!$E$2:$E$929,$B15,Détail!$D$2:$D$929,"Nicolas",Détail!$J$2:$J$929,1) -> 20 | K15: =SUMIFS(Détail!$F$2:$F$929,Détail!$E$2:$E$929,$B15,Détail!$D$2:$D$929,"Aurélie",Détail!$J$2:$J$929,1) -> 15 | L15: =IF(J15+K15-I15<=0,0,IF(F15=1,(J15+K15-I15)/G15,ROUNDUP((J15+K15-I15)/E15,0))) -> 35 | M15: =IF(H15="",0,IF(F15=1,L15/1000*H15,L15*H15)) -> 0.5775 | N15: =SUMIFS(Détail!$F$2:$F$929,Détail!$E$2:$E$929,$B15,Détail!$D$2:$D$929,"Nicolas",Détail!$J$2:$J$929,2) -> 30 | O15: =SUMIFS(Détail!$F$2:$F$929,Détail!$E$2:$E$929,$B15,Détail!$D$2:$D$929,"Aurélie",Détail!$J$2:$J$929,2) -> 20 | P15: =IF(N15+O15-Z15<=0,0,IF(F15=1,(N15+O15-Z15)/G15,ROUNDUP((N15+O15-Z15)/E15,0))) -> 50 | Q15: =IF(H15="",0,IF(F15=1,P15/1000*H15,P15*H15)) -> 0.825 | R15: =J15+N15 -> 50 | S15: =K15+O15 -> 35 | T15: =R15*Y15 -> 0.825 | U15: =S15*Y15 -> 0.5775 | V15: =Z15+IF(F15=1,P15*G15,P15*E15)-(N15+O15) -> 0 | W15: =V15*Y15 -> 0 | Y15: =IF(H15="",0,IF(F15=1,H15/1000/G15,H15/E15)) -> 0.0165 | Z15: =I15+IF(F15=1,L15*G15,L15*E15)-(J15+K15) -> 0
A16: Féculents | B16: Riz (sec) | C16: g | D16: paquet 1 kg | E16: 1000 | F16: 0 | G16: 1 | H16: 2.34 | I16: 0 | J16: =SUMIFS(Détail!$F$2:$F$929,Détail!$E$2:$E$929,$B16,Détail!$D$2:$D$929,"Nicolas",Détail!$J$2:$J$929,1) -> 135 | K16: =SUMIFS(Détail!$F$2:$F$929,Détail!$E$2:$E$929,$B16,Détail!$D$2:$D$929,"Aurélie",Détail!$J$2:$J$929,1) -> 65 | L16: =IF(J16+K16-I16<=0,0,IF(F16=1,(J16+K16-I16)/G16,ROUNDUP((J16+K16-I16)/E16,0))) -> 1 | M16: =IF(H16="",0,IF(F16=1,L16/1000*H16,L16*H16)) -> 2.34 | N16: =SUMIFS(Détail!$F$2:$F$929,Détail!$E$2:$E$929,$B16,Détail!$D$2:$D$929,"Nicolas",Détail!$J$2:$J$929,2) -> 525 | O16: =SUMIFS(Détail!$F$2:$F$929,Détail!$E$2:$E$929,$B16,Détail!$D$2:$D$929,"Aurélie",Détail!$J$2:$J$929,2) -> 265 | P16: =IF(N16+O16-Z16<=0,0,IF(F16=1,(N16+O16-Z16)/G16,ROUNDUP((N16+O16-Z16)/E16,0))) -> 0 | Q16: =IF(H16="",0,IF(F16=1,P16/1000*H16,P16*H16)) -> 0 | R16: =J16+N16 -> 660 | S16: =K16+O16 -> 330 | T16: =R16*Y16 -> 1.5444 | U16: =S16*Y16 -> 0.7722 | V16: =Z16+IF(F16=1,P16*G16,P16*E16)-(N16+O16) -> 10 | W16: =V16*Y16 -> 0.0234 | Y16: =IF(H16="",0,IF(F16=1,H16/1000/G16,H16/E16)) -> 0.00234 | Z16: =I16+IF(F16=1,L16*G16,L16*E16)-(J16+K16) -> 800
A17: Féculents | B17: Pâtes (sèches) | C17: g | D17: paquet 500 g | E17: 500 | F17: 0 | G17: 1 | H17: 1.45 | I17: 0 | J17: =SUMIFS(Détail!$F$2:$F$929,Détail!$E$2:$E$929,$B17,Détail!$D$2:$D$929,"Nicolas",Détail!$J$2:$J$929,1) -> 0 | K17: =SUMIFS(Détail!$F$2:$F$929,Détail!$E$2:$E$929,$B17,Détail!$D$2:$D$929,"Aurélie",Détail!$J$2:$J$929,1) -> 0 | L17: =IF(J17+K17-I17<=0,0,IF(F17=1,(J17+K17-I17)/G17,ROUNDUP((J17+K17-I17)/E17,0))) -> 0 | M17: =IF(H17="",0,IF(F17=1,L17/1000*H17,L17*H17)) -> 0 | N17: =SUMIFS(Détail!$F$2:$F$929,Détail!$E$2:$E$929,$B17,Détail!$D$2:$D$929,"Nicolas",Détail!$J$2:$J$929,2) -> 315 | O17: =SUMIFS(Détail!$F$2:$F$929,Détail!$E$2:$E$929,$B17,Détail!$D$2:$D$929,"Aurélie",Détail!$J$2:$J$929,2) -> 180 | P17: =IF(N17+O17-Z17<=0,0,IF(F17=1,(N17+O17-Z17)/G17,ROUNDUP((N17+O17-Z17)/E17,0))) -> 1 | Q17: =IF(H17="",0,IF(F17=1,P17/1000*H17,P17*H17)) -> 1.45 | R17: =J17+N17 -> 315 | S17: =K17+O17 -> 180 | T17: =R17*Y17 -> 0.9135 | U17: =S17*Y17 -> 0.522 | V17: =Z17+IF(F17=1,P17*G17,P17*E17)-(N17+O17) -> 5 | W17: =V17*Y17 -> 0.0145 | Y17: =IF(H17="",0,IF(F17=1,H17/1000/G17,H17/E17)) -> 0.0029 | Z17: =I17+IF(F17=1,L17*G17,L17*E17)-(J17+K17) -> 0
A18: Féculents | B18: Pâtes à lasagnes (sèches) | C18: g | D18: paquet 500 g | E18: 500 | F18: 0 | G18: 1 | H18: 2.47 | I18: 0 | J18: =SUMIFS(Détail!$F$2:$F$929,Détail!$E$2:$E$929,$B18,Détail!$D$2:$D$929,"Nicolas",Détail!$J$2:$J$929,1) -> 0 | K18: =SUMIFS(Détail!$F$2:$F$929,Détail!$E$2:$E$929,$B18,Détail!$D$2:$D$929,"Aurélie",Détail!$J$2:$J$929,1) -> 0 | L18: =IF(J18+K18-I18<=0,0,IF(F18=1,(J18+K18-I18)/G18,ROUNDUP((J18+K18-I18)/E18,0))) -> 0 | M18: =IF(H18="",0,IF(F18=1,L18/1000*H18,L18*H18)) -> 0 | N18: =SUMIFS(Détail!$F$2:$F$929,Détail!$E$2:$E$929,$B18,Détail!$D$2:$D$929,"Nicolas",Détail!$J$2:$J$929,2) -> 130 | O18: =SUMIFS(Détail!$F$2:$F$929,Détail!$E$2:$E$929,$B18,Détail!$D$2:$D$929,"Aurélie",Détail!$J$2:$J$929,2) -> 90 | P18: =IF(N18+O18-Z18<=0,0,IF(F18=1,(N18+O18-Z18)/G18,ROUNDUP((N18+O18-Z18)/E18,0))) -> 1 | Q18: =IF(H18="",0,IF(F18=1,P18/1000*H18,P18*H18)) -> 2.47 | R18: =J18+N18 -> 130 | S18: =K18+O18 -> 90 | T18: =R18*Y18 -> 0.6422 | U18: =S18*Y18 -> 0.4446 | V18: =Z18+IF(F18=1,P18*G18,P18*E18)-(N18+O18) -> 280 | W18: =V18*Y18 -> 1.3832 | Y18: =IF(H18="",0,IF(F18=1,H18/1000/G18,H18/E18)) -> 0.00494 | Z18: =I18+IF(F18=1,L18*G18,L18*E18)-(J18+K18) -> 0
A19: Féculents | B19: Flocons d'avoine | C19: g | D19: paquet 500 g | E19: 500 | F19: 0 | G19: 1 | H19: 1.71 | I19: 0 | J19: =SUMIFS(Détail!$F$2:$F$929,Détail!$E$2:$E$929,$B19,Détail!$D$2:$D$929,"Nicolas",Détail!$J$2:$J$929,1) -> 325 | K19: =SUMIFS(Détail!$F$2:$F$929,Détail!$E$2:$E$929,$B19,Détail!$D$2:$D$929,"Aurélie",Détail!$J$2:$J$929,1) -> 0 | L19: =IF(J19+K19-I19<=0,0,IF(F19=1,(J19+K19-I19)/G19,ROUNDUP((J19+K19-I19)/E19,0))) -> 1 | M19: =IF(H19="",0,IF(F19=1,L19/1000*H19,L19*H19)) -> 1.71 | N19: =SUMIFS(Détail!$F$2:$F$929,Détail!$E$2:$E$929,$B19,Détail!$D$2:$D$929,"Nicolas",Détail!$J$2:$J$929,2) -> 1040 | O19: =SUMIFS(Détail!$F$2:$F$929,Détail!$E$2:$E$929,$B19,Détail!$D$2:$D$929,"Aurélie",Détail!$J$2:$J$929,2) -> 0 | P19: =IF(N19+O19-Z19<=0,0,IF(F19=1,(N19+O19-Z19)/G19,ROUNDUP((N19+O19-Z19)/E19,0))) -> 2 | Q19: =IF(H19="",0,IF(F19=1,P19/1000*H19,P19*H19)) -> 3.42 | R19: =J19+N19 -> 1365 | S19: =K19+O19 -> 0 | T19: =R19*Y19 -> 4.6683 | U19: =S19*Y19 -> 0 | V19: =Z19+IF(F19=1,P19*G19,P19*E19)-(N19+O19) -> 135 | W19: =V19*Y19 -> 0.4617 | Y19: =IF(H19="",0,IF(F19=1,H19/1000/G19,H19/E19)) -> 0.00342 | Z19: =I19+IF(F19=1,L19*G19,L19*E19)-(J19+K19) -> 175
A20: Féculents | B20: Pommes de terre | C20: g | D20: vrac (g) | E20: 1 | F20: 1 | G20: 1 | H20: 1.45 | I20: 0 | J20: =SUMIFS(Détail!$F$2:$F$929,Détail!$E$2:$E$929,$B20,Détail!$D$2:$D$929,"Nicolas",Détail!$J$2:$J$929,1) -> 1440 | K20: =SUMIFS(Détail!$F$2:$F$929,Détail!$E$2:$E$929,$B20,Détail!$D$2:$D$929,"Aurélie",Détail!$J$2:$J$929,1) -> 600 | L20: =IF(J20+K20-I20<=0,0,IF(F20=1,(J20+K20-I20)/G20,ROUNDUP((J20+K20-I20)/E20,0))) -> 2040 | M20: =IF(H20="",0,IF(F20=1,L20/1000*H20,L20*H20)) -> 2.958 | N20: =SUMIFS(Détail!$F$2:$F$929,Détail!$E$2:$E$929,$B20,Détail!$D$2:$D$929,"Nicolas",Détail!$J$2:$J$929,2) -> 3300 | O20: =SUMIFS(Détail!$F$2:$F$929,Détail!$E$2:$E$929,$B20,Détail!$D$2:$D$929,"Aurélie",Détail!$J$2:$J$929,2) -> 1450 | P20: =IF(N20+O20-Z20<=0,0,IF(F20=1,(N20+O20-Z20)/G20,ROUNDUP((N20+O20-Z20)/E20,0))) -> 4750 | Q20: =IF(H20="",0,IF(F20=1,P20/1000*H20,P20*H20)) -> 6.8875 | R20: =J20+N20 -> 4740 | S20: =K20+O20 -> 2050 | T20: =R20*Y20 -> 6.873 | U20: =S20*Y20 -> 2.9725 | V20: =Z20+IF(F20=1,P20*G20,P20*E20)-(N20+O20) -> 0 | W20: =V20*Y20 -> 0 | X20: Au sec, à l'ombre, loin des oignons : germent vite à la chaleur. | Y20: =IF(H20="",0,IF(F20=1,H20/1000/G20,H20/E20)) -> 0.00145 | Z20: =I20+IF(F20=1,L20*G20,L20*E20)-(J20+K20) -> 0
A21: Féculents | B21: Patates douces | C21: g | D21: vrac (g) | E21: 1 | F21: 1 | G21: 1 | H21: 3.29 | I21: 0 | J21: =SUMIFS(Détail!$F$2:$F$929,Détail!$E$2:$E$929,$B21,Détail!$D$2:$D$929,"Nicolas",Détail!$J$2:$J$929,1) -> 600 | K21: =SUMIFS(Détail!$F$2:$F$929,Détail!$E$2:$E$929,$B21,Détail!$D$2:$D$929,"Aurélie",Détail!$J$2:$J$929,1) -> 280 | L21: =IF(J21+K21-I21<=0,0,IF(F21=1,(J21+K21-I21)/G21,ROUNDUP((J21+K21-I21)/E21,0))) -> 880 | M21: =IF(H21="",0,IF(F21=1,L21/1000*H21,L21*H21)) -> 2.8952 | N21: =SUMIFS(Détail!$F$2:$F$929,Détail!$E$2:$E$929,$B21,Détail!$D$2:$D$929,"Nicolas",Détail!$J$2:$J$929,2) -> 1200 | O21: =SUMIFS(Détail!$F$2:$F$929,Détail!$E$2:$E$929,$B21,Détail!$D$2:$D$929,"Aurélie",Détail!$J$2:$J$929,2) -> 560 | P21: =IF(N21+O21-Z21<=0,0,IF(F21=1,(N21+O21-Z21)/G21,ROUNDUP((N21+O21-Z21)/E21,0))) -> 1760 | Q21: =IF(H21="",0,IF(F21=1,P21/1000*H21,P21*H21)) -> 5.7904 | R21: =J21+N21 -> 1800 | S21: =K21+O21 -> 840 | T21: =R21*Y21 -> 5.922 | U21: =S21*Y21 -> 2.7636 | V21: =Z21+IF(F21=1,P21*G21,P21*E21)-(N21+O21) -> 0 | W21: =V21*Y21 -> 0 | X21: Hors frigo, 1 à 2 semaines. | Y21: =IF(H21="",0,IF(F21=1,H21/1000/G21,H21/E21)) -> 0.00329 | Z21: =I21+IF(F21=1,L21*G21,L21*E21)-(J21+K21) -> 0
A22: Féculents | B22: Wraps | C22: unité | D22: paquet de 8 | E22: 8 | F22: 0 | G22: 1 | H22: 2.74 | I22: 0 | J22: =SUMIFS(Détail!$F$2:$F$929,Détail!$E$2:$E$929,$B22,Détail!$D$2:$D$929,"Nicolas",Détail!$J$2:$J$929,1) -> 0 | K22: =SUMIFS(Détail!$F$2:$F$929,Détail!$E$2:$E$929,$B22,Détail!$D$2:$D$929,"Aurélie",Détail!$J$2:$J$929,1) -> 0 | L22: =IF(J22+K22-I22<=0,0,IF(F22=1,(J22+K22-I22)/G22,ROUNDUP((J22+K22-I22)/E22,0))) -> 0 | M22: =IF(H22="",0,IF(F22=1,L22/1000*H22,L22*H22)) -> 0 | N22: =SUMIFS(Détail!$F$2:$F$929,Détail!$E$2:$E$929,$B22,Détail!$D$2:$D$929,"Nicolas",Détail!$J$2:$J$929,2) -> 4 | O22: =SUMIFS(Détail!$F$2:$F$929,Détail!$E$2:$E$929,$B22,Détail!$D$2:$D$929,"Aurélie",Détail!$J$2:$J$929,2) -> 2 | P22: =IF(N22+O22-Z22<=0,0,IF(F22=1,(N22+O22-Z22)/G22,ROUNDUP((N22+O22-Z22)/E22,0))) -> 1 | Q22: =IF(H22="",0,IF(F22=1,P22/1000*H22,P22*H22)) -> 2.74 | R22: =J22+N22 -> 4 | S22: =K22+O22 -> 2 | T22: =R22*Y22 -> 1.37 | U22: =S22*Y22 -> 0.685 | V22: =Z22+IF(F22=1,P22*G22,P22*E22)-(N22+O22) -> 2 | W22: =V22*Y22 -> 0.685 | X22: Longue conservation fermés. | Y22: =IF(H22="",0,IF(F22=1,H22/1000/G22,H22/E22)) -> 0.3425 | Z22: =I22+IF(F22=1,L22*G22,L22*E22)-(J22+K22) -> 0
A23: Pain | B23: Pains burger | C23: unité | D23: paquet de 2 | E23: 2 | F23: 0 | G23: 1 | H23: 3 | I23: 0 | J23: =SUMIFS(Détail!$F$2:$F$929,Détail!$E$2:$E$929,$B23,Détail!$D$2:$D$929,"Nicolas",Détail!$J$2:$J$929,1) -> 1 | K23: =SUMIFS(Détail!$F$2:$F$929,Détail!$E$2:$E$929,$B23,Détail!$D$2:$D$929,"Aurélie",Détail!$J$2:$J$929,1) -> 1 | L23: =IF(J23+K23-I23<=0,0,IF(F23=1,(J23+K23-I23)/G23,ROUNDUP((J23+K23-I23)/E23,0))) -> 1 | M23: =IF(H23="",0,IF(F23=1,L23/1000*H23,L23*H23)) -> 3 | N23: =SUMIFS(Détail!$F$2:$F$929,Détail!$E$2:$E$929,$B23,Détail!$D$2:$D$929,"Nicolas",Détail!$J$2:$J$929,2) -> 0 | O23: =SUMIFS(Détail!$F$2:$F$929,Détail!$E$2:$E$929,$B23,Détail!$D$2:$D$929,"Aurélie",Détail!$J$2:$J$929,2) -> 0 | P23: =IF(N23+O23-Z23<=0,0,IF(F23=1,(N23+O23-Z23)/G23,ROUNDUP((N23+O23-Z23)/E23,0))) -> 0 | Q23: =IF(H23="",0,IF(F23=1,P23/1000*H23,P23*H23)) -> 0 | R23: =J23+N23 -> 1 | S23: =K23+O23 -> 1 | T23: =R23*Y23 -> 1.5 | U23: =S23*Y23 -> 1.5 | V23: =Z23+IF(F23=1,P23*G23,P23*E23)-(N23+O23) -> 0 | W23: =V23*Y23 -> 0 | X23: Pour le 4 octobre. | Y23: =IF(H23="",0,IF(F23=1,H23/1000/G23,H23/E23)) -> 1.5 | Z23: =I23+IF(F23=1,L23*G23,L23*E23)-(J23+K23) -> 0
A24: Pain | B24: Pain complet | C24: g | D24: pièce ~100 g (hypothèse) | E24: 100 | F24: 0 | G24: 1 | H24: 1.2 | I24: 0 | J24: =SUMIFS(Détail!$F$2:$F$929,Détail!$E$2:$E$929,$B24,Détail!$D$2:$D$929,"Nicolas",Détail!$J$2:$J$929,1) -> 0 | K24: =SUMIFS(Détail!$F$2:$F$929,Détail!$E$2:$E$929,$B24,Détail!$D$2:$D$929,"Aurélie",Détail!$J$2:$J$929,1) -> 200 | L24: =IF(J24+K24-I24<=0,0,IF(F24=1,(J24+K24-I24)/G24,ROUNDUP((J24+K24-I24)/E24,0))) -> 2 | M24: =IF(H24="",0,IF(F24=1,L24/1000*H24,L24*H24)) -> 2.4 | N24: =SUMIFS(Détail!$F$2:$F$929,Détail!$E$2:$E$929,$B24,Détail!$D$2:$D$929,"Nicolas",Détail!$J$2:$J$929,2) -> 0 | O24: =SUMIFS(Détail!$F$2:$F$929,Détail!$E$2:$E$929,$B24,Détail!$D$2:$D$929,"Aurélie",Détail!$J$2:$J$929,2) -> 640 | P24: =IF(N24+O24-Z24<=0,0,IF(F24=1,(N24+O24-Z24)/G24,ROUNDUP((N24+O24-Z24)/E24,0))) -> 7 | Q24: =IF(H24="",0,IF(F24=1,P24/1000*H24,P24*H24)) -> 8.4 | R24: =J24+N24 -> 0 | S24: =K24+O24 -> 840 | T24: =R24*Y24 -> 0 | U24: =S24*Y24 -> 10.08 | V24: =Z24+IF(F24=1,P24*G24,P24*E24)-(N24+O24) -> 60 | W24: =V24*Y24 -> 0.72 | X24: Congeler en tranches, sortir la veille. | Y24: =IF(H24="",0,IF(F24=1,H24/1000/G24,H24/E24)) -> 0.012 | Z24: =I24+IF(F24=1,L24*G24,L24*E24)-(J24+K24) -> 0
A25: Légumes | B25: Haricots verts | C25: g | D25: sachet 440 g surgelé | E25: 440 | F25: 0 | G25: 1 | H25: 1.72 | I25: 0 | J25: =SUMIFS(Détail!$F$2:$F$929,Détail!$E$2:$E$929,$B25,Détail!$D$2:$D$929,"Nicolas",Détail!$J$2:$J$929,1) -> 500 | K25: =SUMIFS(Détail!$F$2:$F$929,Détail!$E$2:$E$929,$B25,Détail!$D$2:$D$929,"Aurélie",Détail!$J$2:$J$929,1) -> 560 | L25: =IF(J25+K25-I25<=0,0,IF(F25=1,(J25+K25-I25)/G25,ROUNDUP((J25+K25-I25)/E25,0))) -> 3 | M25: =IF(H25="",0,IF(F25=1,L25/1000*H25,L25*H25)) -> 5.16 | N25: =SUMIFS(Détail!$F$2:$F$929,Détail!$E$2:$E$929,$B25,Détail!$D$2:$D$929,"Nicolas",Détail!$J$2:$J$929,2) -> 1300 | O25: =SUMIFS(Détail!$F$2:$F$929,Détail!$E$2:$E$929,$B25,Détail!$D$2:$D$929,"Aurélie",Détail!$J$2:$J$929,2) -> 1520 | P25: =IF(N25+O25-Z25<=0,0,IF(F25=1,(N25+O25-Z25)/G25,ROUNDUP((N25+O25-Z25)/E25,0))) -> 6 | Q25: =IF(H25="",0,IF(F25=1,P25/1000*H25,P25*H25)) -> 10.32 | R25: =J25+N25 -> 1800 | S25: =K25+O25 -> 2080 | T25: =R25*Y25 -> 7.0363636 | U25: =S25*Y25 -> 8.1309091 | V25: =Z25+IF(F25=1,P25*G25,P25*E25)-(N25+O25) -> 80 | W25: =V25*Y25 -> 0.31272727 | X25: Surgelés. | Y25: =IF(H25="",0,IF(F25=1,H25/1000/G25,H25/E25)) -> 0.0039090909 | Z25: =I25+IF(F25=1,L25*G25,L25*E25)-(J25+K25) -> 260
A26: Légumes | B26: Carottes | C26: g | D26: vrac (g) | E26: 1 | F26: 1 | G26: 1 | H26: 1.99 | I26: 0 | J26: =SUMIFS(Détail!$F$2:$F$929,Détail!$E$2:$E$929,$B26,Détail!$D$2:$D$929,"Nicolas",Détail!$J$2:$J$929,1) -> 260 | K26: =SUMIFS(Détail!$F$2:$F$929,Détail!$E$2:$E$929,$B26,Détail!$D$2:$D$929,"Aurélie",Détail!$J$2:$J$929,1) -> 320 | L26: =IF(J26+K26-I26<=0,0,IF(F26=1,(J26+K26-I26)/G26,ROUNDUP((J26+K26-I26)/E26,0))) -> 580 | M26: =IF(H26="",0,IF(F26=1,L26/1000*H26,L26*H26)) -> 1.1542 | N26: =SUMIFS(Détail!$F$2:$F$929,Détail!$E$2:$E$929,$B26,Détail!$D$2:$D$929,"Nicolas",Détail!$J$2:$J$929,2) -> 480 | O26: =SUMIFS(Détail!$F$2:$F$929,Détail!$E$2:$E$929,$B26,Détail!$D$2:$D$929,"Aurélie",Détail!$J$2:$J$929,2) -> 610 | P26: =IF(N26+O26-Z26<=0,0,IF(F26=1,(N26+O26-Z26)/G26,ROUNDUP((N26+O26-Z26)/E26,0))) -> 1090 | Q26: =IF(H26="",0,IF(F26=1,P26/1000*H26,P26*H26)) -> 2.1691 | R26: =J26+N26 -> 740 | S26: =K26+O26 -> 930 | T26: =R26*Y26 -> 1.4726 | U26: =S26*Y26 -> 1.8507 | V26: =Z26+IF(F26=1,P26*G26,P26*E26)-(N26+O26) -> 0 | W26: =V26*Y26 -> 0 | X26: 2 à 3 semaines au bac à légumes. | Y26: =IF(H26="",0,IF(F26=1,H26/1000/G26,H26/E26)) -> 0.00199 | Z26: =I26+IF(F26=1,L26*G26,L26*E26)-(J26+K26) -> 0
A27: Légumes | B27: Oignons | C27: g | D27: vrac (g) | E27: 1 | F27: 1 | G27: 1 | H27: 2.49 | I27: 0 | J27: =SUMIFS(Détail!$F$2:$F$929,Détail!$E$2:$E$929,$B27,Détail!$D$2:$D$929,"Nicolas",Détail!$J$2:$J$929,1) -> 160 | K27: =SUMIFS(Détail!$F$2:$F$929,Détail!$E$2:$E$929,$B27,Détail!$D$2:$D$929,"Aurélie",Détail!$J$2:$J$929,1) -> 160 | L27: =IF(J27+K27-I27<=0,0,IF(F27=1,(J27+K27-I27)/G27,ROUNDUP((J27+K27-I27)/E27,0))) -> 320 | M27: =IF(H27="",0,IF(F27=1,L27/1000*H27,L27*H27)) -> 0.7968 | N27: =SUMIFS(Détail!$F$2:$F$929,Détail!$E$2:$E$929,$B27,Détail!$D$2:$D$929,"Nicolas",Détail!$J$2:$J$929,2) -> 540 | O27: =SUMIFS(Détail!$F$2:$F$929,Détail!$E$2:$E$929,$B27,Détail!$D$2:$D$929,"Aurélie",Détail!$J$2:$J$929,2) -> 540 | P27: =IF(N27+O27-Z27<=0,0,IF(F27=1,(N27+O27-Z27)/G27,ROUNDUP((N27+O27-Z27)/E27,0))) -> 1080 | Q27: =IF(H27="",0,IF(F27=1,P27/1000*H27,P27*H27)) -> 2.6892 | R27: =J27+N27 -> 700 | S27: =K27+O27 -> 700 | T27: =R27*Y27 -> 1.743 | U27: =S27*Y27 -> 1.743 | V27: =Z27+IF(F27=1,P27*G27,P27*E27)-(N27+O27) -> 0 | W27: =V27*Y27 -> 0 | X27: Plusieurs semaines au sec. | Y27: =IF(H27="",0,IF(F27=1,H27/1000/G27,H27/E27)) -> 0.00249 | Z27: =I27+IF(F27=1,L27*G27,L27*E27)-(J27+K27) -> 0
A28: Légumes | B28: Maïs | C28: g | D28: boîte (~140 g égouttés) | E28: 140 | F28: 0 | G28: 1 | H28: 0.89 | I28: 0 | J28: =SUMIFS(Détail!$F$2:$F$929,Détail!$E$2:$E$929,$B28,Détail!$D$2:$D$929,"Nicolas",Détail!$J$2:$J$929,1) -> 40 | K28: =SUMIFS(Détail!$F$2:$F$929,Détail!$E$2:$E$929,$B28,Détail!$D$2:$D$929,"Aurélie",Détail!$J$2:$J$929,1) -> 30 | L28: =IF(J28+K28-I28<=0,0,IF(F28=1,(J28+K28-I28)/G28,ROUNDUP((J28+K28-I28)/E28,0))) -> 1 | M28: =IF(H28="",0,IF(F28=1,L28/1000*H28,L28*H28)) -> 0.89 | N28: =SUMIFS(Détail!$F$2:$F$929,Détail!$E$2:$E$929,$B28,Détail!$D$2:$D$929,"Nicolas",Détail!$J$2:$J$929,2) -> 40 | O28: =SUMIFS(Détail!$F$2:$F$929,Détail!$E$2:$E$929,$B28,Détail!$D$2:$D$929,"Aurélie",Détail!$J$2:$J$929,2) -> 30 | P28: =IF(N28+O28-Z28<=0,0,IF(F28=1,(N28+O28-Z28)/G28,ROUNDUP((N28+O28-Z28)/E28,0))) -> 0 | Q28: =IF(H28="",0,IF(F28=1,P28/1000*H28,P28*H28)) -> 0 | R28: =J28+N28 -> 80 | S28: =K28+O28 -> 60 | T28: =R28*Y28 -> 0.50857143 | U28: =S28*Y28 -> 0.38142857 | V28: =Z28+IF(F28=1,P28*G28,P28*E28)-(N28+O28) -> 0 | W28: =V28*Y28 -> 0 | X28: Conserve. | Y28: =IF(H28="",0,IF(F28=1,H28/1000/G28,H28/E28)) -> 0.0063571429 | Z28: =I28+IF(F28=1,L28*G28,L28*E28)-(J28+K28) -> 70
A29: Légumes | B29: Tomates | C29: g | D29: vrac (g) | E29: 1 | F29: 1 | G29: 1 | H29: 2.79 | I29: 0 | J29: =SUMIFS(Détail!$F$2:$F$929,Détail!$E$2:$E$929,$B29,Détail!$D$2:$D$929,"Nicolas",Détail!$J$2:$J$929,1) -> 630 | K29: =SUMIFS(Détail!$F$2:$F$929,Détail!$E$2:$E$929,$B29,Détail!$D$2:$D$929,"Aurélie",Détail!$J$2:$J$929,1) -> 1190 | L29: =IF(J29+K29-I29<=0,0,IF(F29=1,(J29+K29-I29)/G29,ROUNDUP((J29+K29-I29)/E29,0))) -> 1820 | M29: =IF(H29="",0,IF(F29=1,L29/1000*H29,L29*H29)) -> 5.0778 | N29: =SUMIFS(Détail!$F$2:$F$929,Détail!$E$2:$E$929,$B29,Détail!$D$2:$D$929,"Nicolas",Détail!$J$2:$J$929,2) -> 2770 | O29: =SUMIFS(Détail!$F$2:$F$929,Détail!$E$2:$E$929,$B29,Détail!$D$2:$D$929,"Aurélie",Détail!$J$2:$J$929,2) -> 4600 | P29: =IF(N29+O29-Z29<=0,0,IF(F29=1,(N29+O29-Z29)/G29,ROUNDUP((N29+O29-Z29)/E29,0))) -> 7370 | Q29: =IF(H29="",0,IF(F29=1,P29/1000*H29,P29*H29)) -> 20.5623 | R29: =J29+N29 -> 3400 | S29: =K29+O29 -> 5790 | T29: =R29*Y29 -> 9.486 | U29: =S29*Y29 -> 16.1541 | V29: =Z29+IF(F29=1,P29*G29,P29*E29)-(N29+O29) -> 0 | W29: =V29*Y29 -> 0 | X29: Risque sur 16 jours : en prendre une partie peu mûre ; pour les plats cuits de fin de période, la conserve fait l'affaire. | Y29: =IF(H29="",0,IF(F29=1,H29/1000/G29,H29/E29)) -> 0.00279 | Z29: =I29+IF(F29=1,L29*G29,L29*E29)-(J29+K29) -> 0
A30: Légumes | B30: Courgettes | C30: g | D30: vrac (g) | E30: 1 | F30: 1 | G30: 1 | H30: 1.49 | I30: 0 | J30: =SUMIFS(Détail!$F$2:$F$929,Détail!$E$2:$E$929,$B30,Détail!$D$2:$D$929,"Nicolas",Détail!$J$2:$J$929,1) -> 320 | K30: =SUMIFS(Détail!$F$2:$F$929,Détail!$E$2:$E$929,$B30,Détail!$D$2:$D$929,"Aurélie",Détail!$J$2:$J$929,1) -> 370 | L30: =IF(J30+K30-I30<=0,0,IF(F30=1,(J30+K30-I30)/G30,ROUNDUP((J30+K30-I30)/E30,0))) -> 690 | M30: =IF(H30="",0,IF(F30=1,L30/1000*H30,L30*H30)) -> 1.0281 | N30: =SUMIFS(Détail!$F$2:$F$929,Détail!$E$2:$E$929,$B30,Détail!$D$2:$D$929,"Nicolas",Détail!$J$2:$J$929,2) -> 1470 | O30: =SUMIFS(Détail!$F$2:$F$929,Détail!$E$2:$E$929,$B30,Détail!$D$2:$D$929,"Aurélie",Détail!$J$2:$J$929,2) -> 1760 | P30: =IF(N30+O30-Z30<=0,0,IF(F30=1,(N30+O30-Z30)/G30,ROUNDUP((N30+O30-Z30)/E30,0))) -> 3230 | Q30: =IF(H30="",0,IF(F30=1,P30/1000*H30,P30*H30)) -> 4.8127 | R30: =J30+N30 -> 1790 | S30: =K30+O30 -> 2130 | T30: =R30*Y30 -> 2.6671 | U30: =S30*Y30 -> 3.1737 | V30: =Z30+IF(F30=1,P30*G30,P30*E30)-(N30+O30) -> 0 | W30: =V30*Y30 -> 0 | X30: Risque sur 16 jours (~1 semaine au frigo) : congeler crues en rondelles celles des plats cuits de la 2e semaine. | Y30: =IF(H30="",0,IF(F30=1,H30/1000/G30,H30/E30)) -> 0.00149 | Z30: =I30+IF(F30=1,L30*G30,L30*E30)-(J30+K30) -> 0
A31: Légumes | B31: Poivrons | C31: g | D31: vrac (g) | E31: 1 | F31: 1 | G31: 1 | H31: 13.98 | I31: 0 | J31: =SUMIFS(Détail!$F$2:$F$929,Détail!$E$2:$E$929,$B31,Détail!$D$2:$D$929,"Nicolas",Détail!$J$2:$J$929,1) -> 110 | K31: =SUMIFS(Détail!$F$2:$F$929,Détail!$E$2:$E$929,$B31,Détail!$D$2:$D$929,"Aurélie",Détail!$J$2:$J$929,1) -> 140 | L31: =IF(J31+K31-I31<=0,0,IF(F31=1,(J31+K31-I31)/G31,ROUNDUP((J31+K31-I31)/E31,0))) -> 250 | M31: =IF(H31="",0,IF(F31=1,L31/1000*H31,L31*H31)) -> 3.495 | N31: =SUMIFS(Détail!$F$2:$F$929,Détail!$E$2:$E$929,$B31,Détail!$D$2:$D$929,"Nicolas",Détail!$J$2:$J$929,2) -> 330 | O31: =SUMIFS(Détail!$F$2:$F$929,Détail!$E$2:$E$929,$B31,Détail!$D$2:$D$929,"Aurélie",Détail!$J$2:$J$929,2) -> 420 | P31: =IF(N31+O31-Z31<=0,0,IF(F31=1,(N31+O31-Z31)/G31,ROUNDUP((N31+O31-Z31)/E31,0))) -> 750 | Q31: =IF(H31="",0,IF(F31=1,P31/1000*H31,P31*H31)) -> 10.485 | R31: =J31+N31 -> 440 | S31: =K31+O31 -> 560 | T31: =R31*Y31 -> 6.1512 | U31: =S31*Y31 -> 7.8288 | V31: =Z31+IF(F31=1,P31*G31,P31*E31)-(N31+O31) -> 0 | W31: =V31*Y31 -> 0 | X31: 13,98 €/kg. 1 à 2 semaines au frigo, se congèlent crus en lanières. | Y31: =IF(H31="",0,IF(F31=1,H31/1000/G31,H31/E31)) -> 0.01398 | Z31: =I31+IF(F31=1,L31*G31,L31*E31)-(J31+K31) -> 0
... A40: Desserts | B40: Glace | C40: g | D40: bac 500 g | E40: 500 | F40: 0 | G40: 1 | H40: 2.49 | I40: 0 | J40: =SUMIFS(Détail!$F$2:$F$929,Détail!$E$2:$E$929,$B40,Détail!$D$2:$D$929,"Nicolas",Détail!$J$2:$J$929,1) -> 75 | K40: =SUMIFS(Détail!$F$2:$F$929,Détail!$E$2:$E$929,$B40,Détail!$D$2:$D$929,"Aurélie",Détail!$J$2:$J$929,1) -> 55 | L40: =IF(J40+K40-I40<=0,0,IF(F40=1,(J40+K40-I40)/G40,ROUNDUP((J40+K40-I40)/E40,0))) -> 1 | M40: =IF(H40="",0,IF(F40=1,L40/1000*H40,L40*H40)) -> 2.49 | N40: =SUMIFS(Détail!$F$2:$F$929,Détail!$E$2:$E$929,$B40,Détail!$D$2:$D$929,"Nicolas",Détail!$J$2:$J$929,2) -> 150 | O40: =SUMIFS(Détail!$F$2:$F$929,Détail!$E$2:$E$929,$B40,Détail!$D$2:$D$929,"Aurélie",Détail!$J$2:$J$929,2) -> 110 | P40: =IF(N40+O40-Z40<=0,0,IF(F40=1,(N40+O40-Z40)/G40,ROUNDUP((N40+O40-Z40)/E40,0))) -> 0 | Q40: =IF(H40="",0,IF(F40=1,P40/1000*H40,P40*H40)) -> 0 | R40: =J40+N40 -> 225 | S40: =K40+O40 -> 165 | T40: =R40*Y40 -> 1.1205 | U40: =S40*Y40 -> 0.8217 | V40: =Z40+IF(F40=1,P40*G40,P40*E40)-(N40+O40) -> 110 | W40: =V40*Y40 -> 0.5478 | X40: Congélateur. | Y40: =IF(H40="",0,IF(F40=1,H40/1000/G40,H40/E40)) -> 0.00498 | Z40: =I40+IF(F40=1,L40*G40,L40*E40)-(J40+K40) -> 370
A41: Desserts | B41: Chocolat noir | C41: g | D41: 500 g | E41: 500 | F41: 0 | G41: 1 | H41: 5.26 | I41: 0 | J41: =SUMIFS(Détail!$F$2:$F$929,Détail!$E$2:$E$929,$B41,Détail!$D$2:$D$929,"Nicolas",Détail!$J$2:$J$929,1) -> 20 | K41: =SUMIFS(Détail!$F$2:$F$929,Détail!$E$2:$E$929,$B41,Détail!$D$2:$D$929,"Aurélie",Détail!$J$2:$J$929,1) -> 20 | L41: =IF(J41+K41-I41<=0,0,IF(F41=1,(J41+K41-I41)/G41,ROUNDUP((J41+K41-I41)/E41,0))) -> 1 | M41: =IF(H41="",0,IF(F41=1,L41/1000*H41,L41*H41)) -> 5.26 | N41: =SUMIFS(Détail!$F$2:$F$929,Détail!$E$2:$E$929,$B41,Détail!$D$2:$D$929,"Nicolas",Détail!$J$2:$J$929,2) -> 120 | O41: =SUMIFS(Détail!$F$2:$F$929,Détail!$E$2:$E$929,$B41,Détail!$D$2:$D$929,"Aurélie",Détail!$J$2:$J$929,2) -> 100 | P41: =IF(N41+O41-Z41<=0,0,IF(F41=1,(N41+O41-Z41)/G41,ROUNDUP((N41+O41-Z41)/E41,0))) -> 0 | Q41: =IF(H41="",0,IF(F41=1,P41/1000*H41,P41*H41)) -> 0 | R41: =J41+N41 -> 140 | S41: =K41+O41 -> 120 | T41: =R41*Y41 -> 1.4728 | U41: =S41*Y41 -> 1.2624 | V41: =Z41+IF(F41=1,P41*G41,P41*E41)-(N41+O41) -> 240 | W41: =V41*Y41 -> 2.5248 | Y41: =IF(H41="",0,IF(F41=1,H41/1000/G41,H41/E41)) -> 0.01052 | Z41: =I41+IF(F41=1,L41*G41,L41*E41)-(J41+K41) -> 460
A42: Épicerie | B42: Café | C42: g | D42: paquet 1 kg | E42: 1000 | F42: 0 | G42: 1 | H42: 16 | I42: 0 | J42: 238 | K42: 0 | L42: =IF(J42+K42-I42<=0,0,IF(F42=1,(J42+K42-I42)/G42,ROUNDUP((J42+K42-I42)/E42,0))) -> 1 | M42: =IF(H42="",0,IF(F42=1,L42/1000*H42,L42*H42)) -> 16 | N42: 762 | O42: 0 | P42: =IF(N42+O42-Z42<=0,0,IF(F42=1,(N42+O42-Z42)/G42,ROUNDUP((N42+O42-Z42)/E42,0))) -> 0 | Q42: =IF(H42="",0,IF(F42=1,P42/1000*H42,P42*H42)) -> 0 | R42: =J42+N42 -> 1000 | S42: =K42+O42 -> 0 | T42: =R42*Y42 -> 16 | U42: =S42*Y42 -> 0 | V42: =Z42+IF(F42=1,P42*G42,P42*E42)-(N42+O42) -> 0 | W42: =V42*Y42 -> 0 | X42: Hors menu : 100 % Nicolas (modifiable). | Y42: =IF(H42="",0,IF(F42=1,H42/1000/G42,H42/E42)) -> 0.016 | Z42: =I42+IF(F42=1,L42*G42,L42*E42)-(J42+K42) -> 762
A43: Épicerie | B43: Eau (bouteilles 5 L) | C43: L | D43: bouteille 5 L | E43: 5 | F43: 0 | G43: 1 | H43: 1.54 | I43: 0 | J43: 10 | K43: 10 | L43: =IF(J43+K43-I43<=0,0,IF(F43=1,(J43+K43-I43)/G43,ROUNDUP((J43+K43-I43)/E43,0))) -> 4 | M43: =IF(H43="",0,IF(F43=1,L43/1000*H43,L43*H43)) -> 6.16 | N43: 32 | O43: 32 | P43: =IF(N43+O43-Z43<=0,0,IF(F43=1,(N43+O43-Z43)/G43,ROUNDUP((N43+O43-Z43)/E43,0))) -> 13 | Q43: =IF(H43="",0,IF(F43=1,P43/1000*H43,P43*H43)) -> 20.02 | R43: =J43+N43 -> 42 | S43: =K43+O43 -> 42 | T43: =R43*Y43 -> 12.936 | U43: =S43*Y43 -> 12.936 | V43: =Z43+IF(F43=1,P43*G43,P43*E43)-(N43+O43) -> 1 | W43: =V43*Y43 -> 0.308 | X43: Hors menu : moitié chacun (modifiable). | Y43: =IF(H43="",0,IF(F43=1,H43/1000/G43,H43/E43)) -> 0.308 | Z43: =I43+IF(F43=1,L43*G43,L43*E43)-(J43+K43) -> 0
A44: Épicerie | B44: Citrons | C44: unité | D44: pièce | E44: 1 | F44: 0 | G44: 1 | I44: 0 | J44: 1 | K44: 1 | L44: =IF(J44+K44-I44<=0,0,IF(F44=1,(J44+K44-I44)/G44,ROUNDUP((J44+K44-I44)/E44,0))) -> 2 | M44: =IF(H44="",0,IF(F44=1,L44/1000*H44,L44*H44)) -> 0 | N44: 2 | O44: 2 | P44: =IF(N44+O44-Z44<=0,0,IF(F44=1,(N44+O44-Z44)/G44,ROUNDUP((N44+O44-Z44)/E44,0))) -> 4 | Q44: =IF(H44="",0,IF(F44=1,P44/1000*H44,P44*H44)) -> 0 | R44: =J44+N44 -> 3 | S44: =K44+O44 -> 3 | T44: =R44*Y44 -> 0 | U44: =S44*Y44 -> 0 | V44: =Z44+IF(F44=1,P44*G44,P44*E44)-(N44+O44) -> 0 | W44: =V44*Y44 -> 0 | X44: Prix à saisir. Poulet citronné, poisson. | Y44: =IF(H44="",0,IF(F44=1,H44/1000/G44,H44/E44)) -> 0 | Z44: =I44+IF(F44=1,L44*G44,L44*E44)-(J44+K44) -> 0
A45: Épicerie | B45: Sauce soja | C45: unité | D45: flacon | E45: 1 | F45: 0 | G45: 1 | I45: 0 | J45: 0.5 | K45: 0.5 | L45: =IF(J45+K45-I45<=0,0,IF(F45=1,(J45+K45-I45)/G45,ROUNDUP((J45+K45-I45)/E45,0))) -> 1 | M45: =IF(H45="",0,IF(F45=1,L45/1000*H45,L45*H45)) -> 0 | N45: 0 | O45: 0 | P45: =IF(N45+O45-Z45<=0,0,IF(F45=1,(N45+O45-Z45)/G45,ROUNDUP((N45+O45-Z45)/E45,0))) -> 0 | Q45: =IF(H45="",0,IF(F45=1,P45/1000*H45,P45*H45)) -> 0 | R45: =J45+N45 -> 0.5 | S45: =K45+O45 -> 0.5 | T45: =R45*Y45 -> 0 | U45: =S45*Y45 -> 0 | V45: =Z45+IF(F45=1,P45*G45,P45*E45)-(N45+O45) -> 0 | W45: =V45*Y45 -> 0 | X45: Prix à saisir. Partagé 50/50. | Y45: =IF(H45="",0,IF(F45=1,H45/1000/G45,H45/E45)) -> 0 | Z45: =I45+IF(F45=1,L45*G45,L45*E45)-(J45+K45) -> 0
A46: Épicerie | B46: Concentré de tomate | C46: unité | D46: tube ou boîte | E46: 1 | F46: 0 | G46: 1 | I46: 0 | J46: 0.5 | K46: 0.5 | L46: =IF(J46+K46-I46<=0,0,IF(F46=1,(J46+K46-I46)/G46,ROUNDUP((J46+K46-I46)/E46,0))) -> 1 | M46: =IF(H46="",0,IF(F46=1,L46/1000*H46,L46*H46)) -> 0 | N46: 0 | O46: 0 | P46: =IF(N46+O46-Z46<=0,0,IF(F46=1,(N46+O46-Z46)/G46,ROUNDUP((N46+O46-Z46)/E46,0))) -> 0 | Q46: =IF(H46="",0,IF(F46=1,P46/1000*H46,P46*H46)) -> 0 | R46: =J46+N46 -> 0.5 | S46: =K46+O46 -> 0.5 | T46: =R46*Y46 -> 0 | U46: =S46*Y46 -> 0 | V46: =Z46+IF(F46=1,P46*G46,P46*E46)-(N46+O46) -> 0 | W46: =V46*Y46 -> 0 | X46: Prix à saisir. Partagé 50/50. | Y46: =IF(H46="",0,IF(F46=1,H46/1000/G46,H46/E46)) -> 0 | Z46: =I46+IF(F46=1,L46*G46,L46*E46)-(J46+K46) -> 0
A47: Épicerie | B47: Moutarde / ketchup | C47: unité | D47: flacon | E47: 1 | F47: 0 | G47: 1 | I47: 0 | J47: 0.5 | K47: 0.5 | L47: =IF(J47+K47-I47<=0,0,IF(F47=1,(J47+K47-I47)/G47,ROUNDUP((J47+K47-I47)/E47,0))) -> 1 | M47: =IF(H47="",0,IF(F47=1,L47/1000*H47,L47*H47)) -> 0 | N47: 0 | O47: 0 | P47: =IF(N47+O47-Z47<=0,0,IF(F47=1,(N47+O47-Z47)/G47,ROUNDUP((N47+O47-Z47)/E47,0))) -> 0 | Q47: =IF(H47="",0,IF(F47=1,P47/1000*H47,P47*H47)) -> 0 | R47: =J47+N47 -> 0.5 | S47: =K47+O47 -> 0.5 | T47: =R47*Y47 -> 0 | U47: =S47*Y47 -> 0 | V47: =Z47+IF(F47=1,P47*G47,P47*E47)-(N47+O47) -> 0 | W47: =V47*Y47 -> 0 | X47: Prix à saisir. Burger du 4. | Y47: =IF(H47="",0,IF(F47=1,H47/1000/G47,H47/E47)) -> 0 | Z47: =I47+IF(F47=1,L47*G47,L47*E47)-(J47+K47) -> 0
A48: Épicerie | B48: Ail, gingembre, curcuma | C48: unité | D48: si pas en stock | E48: 1 | F48: 0 | G48: 1 | I48: 0 | J48: 0.5 | K48: 0.5 | L48: =IF(J48+K48-I48<=0,0,IF(F48=1,(J48+K48-I48)/G48,ROUNDUP((J48+K48-I48)/E48,0))) -> 1 | M48: =IF(H48="",0,IF(F48=1,L48/1000*H48,L48*H48)) -> 0 | N48: 0 | O48: 0 | P48: =IF(N48+O48-Z48<=0,0,IF(F48=1,(N48+O48-Z48)/G48,ROUNDUP((N48+O48-Z48)/E48,0))) -> 0 | Q48: =IF(H48="",0,IF(F48=1,P48/1000*H48,P48*H48)) -> 0 | R48: =J48+N48 -> 0.5 | S48: =K48+O48 -> 0.5 | T48: =R48*Y48 -> 0 | U48: =S48*Y48 -> 0 | V48: =Z48+IF(F48=1,P48*G48,P48*E48)-(N48+O48) -> 0 | W48: =V48*Y48 -> 0 | X48: Prix à saisir. Partagé 50/50. | Y48: =IF(H48="",0,IF(F48=1,H48/1000/G48,H48/E48)) -> 0 | Z48: =I48+IF(F48=1,L48*G48,L48*E48)-(J48+K48) -> 0
A49: Épicerie | B49: Levure boulangère | C49: unité | D49: sachet | E49: 1 | F49: 0 | G49: 1 | I49: 0 | J49: 0 | K49: 0 | L49: =IF(J49+K49-I49<=0,0,IF(F49=1,(J49+K49-I49)/G49,ROUNDUP((J49+K49-I49)/E49,0))) -> 0 | M49: =IF(H49="",0,IF(F49=1,L49/1000*H49,L49*H49)) -> 0 | N49: 0.5 | O49: 0.5 | P49: =IF(N49+O49-Z49<=0,0,IF(F49=1,(N49+O49-Z49)/G49,ROUNDUP((N49+O49-Z49)/E49,0))) -> 1 | Q49: =IF(H49="",0,IF(F49=1,P49/1000*H49,P49*H49)) -> 0 | R49: =J49+N49 -> 0.5 | S49: =K49+O49 -> 0.5 | T49: =R49*Y49 -> 0 | U49: =S49*Y49 -> 0 | V49: =Z49+IF(F49=1,P49*G49,P49*E49)-(N49+O49) -> 0 | W49: =V49*Y49 -> 0 | X49: Prix à saisir. Pizza du 11. | Y49: =IF(H49="",0,IF(F49=1,H49/1000/G49,H49/E49)) -> 0 | Z49: =I49+IF(F49=1,L49*G49,L49*E49)-(J49+K49) -> 0
A50: Déjà en stock | B50: Lentilles (égouttées) | C50: g | D50: 3 boîtes de 530 g | E50: 530 | F50: 0 | G50: 1 | H50: 0 | I50: 1590 | J50: =SUMIFS(Détail!$F$2:$F$929,Détail!$E$2:$E$929,$B50,Détail!$D$2:$D$929,"Nicolas",Détail!$J$2:$J$929,1) -> 290 | K50: =SUMIFS(Détail!$F$2:$F$929,Détail!$E$2:$E$929,$B50,Détail!$D$2:$D$929,"Aurélie",Détail!$J$2:$J$929,1) -> 240 | L50: =IF(J50+K50-I50<=0,0,IF(F50=1,(J50+K50-I50)/G50,ROUNDUP((J50+K50-I50)/E50,0))) -> 0 | M50: =IF(H50="",0,IF(F50=1,L50/1000*H50,L50*H50)) -> 0 | N50: =SUMIFS(Détail!$F$2:$F$929,Détail!$E$2:$E$929,$B50,Détail!$D$2:$D$929,"Nicolas",Détail!$J$2:$J$929,2) -> 580 | O50: =SUMIFS(Détail!$F$2:$F$929,Détail!$E$2:$E$929,$B50,Détail!$D$2:$D$929,"Aurélie",Détail!$J$2:$J$929,2) -> 480 | P50: =IF(N50+O50-Z50<=0,0,IF(F50=1,(N50+O50-Z50)/G50,ROUNDUP((N50+O50-Z50)/E50,0))) -> 0 | Q50: =IF(H50="",0,IF(F50=1,P50/1000*H50,P50*H50)) -> 0 | R50: =J50+N50 -> 870 | S50: =K50+O50 -> 720 | T50: =R50*Y50 -> 0 | U50: =S50*Y50 -> 0 | V50: =Z50+IF(F50=1,P50*G50,P50*E50)-(N50+O50) -> 0 | W50: =V50*Y50 -> 0 | X50: Ton stock, utilisé en entier. | Y50: =IF(H50="",0,IF(F50=1,H50/1000/G50,H50/E50)) -> 0 | Z50: =I50+IF(F50=1,L50*G50,L50*E50)-(J50+K50) -> 1060
A51: Déjà en stock | B51: Huile | C51: g | D51: stock | E51: 1000 | F51: 0 | G51: 1 | H51: 0 | I51: 1000 | J51: =SUMIFS(Détail!$F$2:$F$929,Détail!$E$2:$E$929,$B51,Détail!$D$2:$D$929,"Nicolas",Détail!$J$2:$J$929,1) -> 92 | K51: =SUMIFS(Détail!$F$2:$F$929,Détail!$E$2:$E$929,$B51,Détail!$D$2:$D$929,"Aurélie",Détail!$J$2:$J$929,1) -> 65 | L51: =IF(J51+K51-I51<=0,0,IF(F51=1,(J51+K51-I51)/G51,ROUNDUP((J51+K51-I51)/E51,0))) -> 0 | M51: =IF(H51="",0,IF(F51=1,L51/1000*H51,L51*H51)) -> 0 | N51: =SUMIFS(Détail!$F$2:$F$929,Détail!$E$2:$E$929,$B51,Détail!$D$2:$D$929,"Nicolas",Détail!$J$2:$J$929,2) -> 301 | O51: =SUMIFS(Détail!$F$2:$F$929,Détail!$E$2:$E$929,$B51,Détail!$D$2:$D$929,"Aurélie",Détail!$J$2:$J$929,2) -> 211 | P51: =IF(N51+O51-Z51<=0,0,IF(F51=1,(N51+O51-Z51)/G51,ROUNDUP((N51+O51-Z51)/E51,0))) -> 0 | Q51: =IF(H51="",0,IF(F51=1,P51/1000*H51,P51*H51)) -> 0 | R51: =J51+N51 -> 393 | S51: =K51+O51 -> 276 | T51: =R51*Y51 -> 0 | U51: =S51*Y51 -> 0 | V51: =Z51+IF(F51=1,P51*G51,P51*E51)-(N51+O51) -> 331 | W51: =V51*Y51 -> 0 | X51: Vérifie qu'il en reste ~700 g. | Y51: =IF(H51="",0,IF(F51=1,H51/1000/G51,H51/E51)) -> 0 | Z51: =I51+IF(F51=1,L51*G51,L51*E51)-(J51+K51) -> 843
A52: Déjà en stock | B52: Farine | C52: g | D52: stock | E52: 1000 | F52: 0 | G52: 1 | H52: 0 | I52: 500 | J52: =SUMIFS(Détail!$F$2:$F$929,Détail!$E$2:$E$929,$B52,Détail!$D$2:$D$929,"Nicolas",Détail!$J$2:$J$929,1) -> 0 | K52: =SUMIFS(Détail!$F$2:$F$929,Détail!$E$2:$E$929,$B52,Détail!$D$2:$D$929,"Aurélie",Détail!$J$2:$J$929,1) -> 0 | L52: =IF(J52+K52-I52<=0,0,IF(F52=1,(J52+K52-I52)/G52,ROUNDUP((J52+K52-I52)/E52,0))) -> 0 | M52: =IF(H52="",0,IF(F52=1,L52/1000*H52,L52*H52)) -> 0 | N52: =SUMIFS(Détail!$F$2:$F$929,Détail!$E$2:$E$929,$B52,Détail!$D$2:$D$929,"Nicolas",Détail!$J$2:$J$929,2) -> 176 | O52: =SUMIFS(Détail!$F$2:$F$929,Détail!$E$2:$E$929,$B52,Détail!$D$2:$D$929,"Aurélie",Détail!$J$2:$J$929,2) -> 112 | P52: =IF(N52+O52-Z52<=0,0,IF(F52=1,(N52+O52-Z52)/G52,ROUNDUP((N52+O52-Z52)/E52,0))) -> 0 | Q52: =IF(H52="",0,IF(F52=1,P52/1000*H52,P52*H52)) -> 0 | R52: =J52+N52 -> 176 | S52: =K52+O52 -> 112 | T52: =R52*Y52 -> 0 | U52: =S52*Y52 -> 0 | V52: =Z52+IF(F52=1,P52*G52,P52*E52)-(N52+O52) -> 212 | W52: =V52*Y52 -> 0 | X52: Pizza, quiche, béchamel. | Y52: =IF(H52="",0,IF(F52=1,H52/1000/G52,H52/E52)) -> 0 | Z52: =I52+IF(F52=1,L52*G52,L52*E52)-(J52+K52) -> 500
B54: Dépense en magasin (€) | M54: =SUM(M6:M52) -> 129.9301 | Q54: =SUM(Q6:Q52) -> 233.18093 | T54: =SUM(T6:T52) -> 176.91886 | U54: =SUM(U6:U52) -> 167.84261 | W54: =SUM(W6:W52) -> 18.349558
B55: Consommation — Nicolas (€) | M55: =SUMPRODUCT(J6:J52,$Y$6:$Y$52) -> 42.986312 | Q55: =SUMPRODUCT(N6:N52,$Y$6:$Y$52) -> 133.93255
B56: Consommation — Aurélie (€) | M56: =SUMPRODUCT(K6:K52,$Y$6:$Y$52) -> 40.369641 | Q56: =SUMPRODUCT(O6:O52,$Y$6:$Y$52) -> 127.47297
B57: Dépense totale sur 21 jours (€) | M57: =M54+Q54 -> 363.11103

Sheet Nutrition
A1: Apports estimés par jour
A2: Repères : Nicolas 1 850-1 950 kcal et 110 g de protéines ou plus ; Aurélie 1 350-1 450 kcal et 85 g ou plus (Mifflin-St Jeor, activité légère, déficit ~500 kcal). Estimations, pas des prescriptions.
A4: Date | B4: Nicolas kcal | C4: Nicolas protéines (g) | D4: Aurélie kcal | E4: Aurélie protéines (g)
A5: 46296 | B5: =SUMIFS(Détail!$H$2:$H$929,Détail!$A$2:$A$929,$A5,Détail!$D$2:$D$929,"Nicolas") -> 1813.2 | C5: =SUMIFS(Détail!$I$2:$I$929,Détail!$A$2:$A$929,$A5,Détail!$D$2:$D$929,"Nicolas") -> 111.26 | D5: =SUMIFS(Détail!$H$2:$H$929,Détail!$A$2:$A$929,$A5,Détail!$D$2:$D$929,"Aurélie") -> 1293.8 | E5: =SUMIFS(Détail!$I$2:$I$929,Détail!$A$2:$A$929,$A5,Détail!$D$2:$D$929,"Aurélie") -> 94.895
A6: 46297 | B6: =SUMIFS(Détail!$H$2:$H$929,Détail!$A$2:$A$929,$A6,Détail!$D$2:$D$929,"Nicolas") -> 1812.2 | C6: =SUMIFS(Détail!$I$2:$I$929,Détail!$A$2:$A$929,$A6,Détail!$D$2:$D$929,"Nicolas") -> 97.395 | D6: =SUMIFS(Détail!$H$2:$H$929,Détail!$A$2:$A$929,$A6,Détail!$D$2:$D$929,"Aurélie") -> 1255.7 | E6: =SUMIFS(Détail!$I$2:$I$929,Détail!$A$2:$A$929,$A6,Détail!$D$2:$D$929,"Aurélie") -> 79.18
A7: 46298 | B7: =SUMIFS(Détail!$H$2:$H$929,Détail!$A$2:$A$929,$A7,Détail!$D$2:$D$929,"Nicolas") -> 1868.55 | C7: =SUMIFS(Détail!$I$2:$I$929,Détail!$A$2:$A$929,$A7,Détail!$D$2:$D$929,"Nicolas") -> 93.805 | D7: =SUMIFS(Détail!$H$2:$H$929,Détail!$A$2:$A$929,$A7,Détail!$D$2:$D$929,"Aurélie") -> 1351.15 | E7: =SUMIFS(Détail!$I$2:$I$929,Détail!$A$2:$A$929,$A7,Détail!$D$2:$D$929,"Aurélie") -> 80.15
A8: 46299 | B8: =SUMIFS(Détail!$H$2:$H$929,Détail!$A$2:$A$929,$A8,Détail!$D$2:$D$929,"Nicolas") -> 1920.2 | C8: =SUMIFS(Détail!$I$2:$I$929,Détail!$A$2:$A$929,$A8,Détail!$D$2:$D$929,"Nicolas") -> 113.23 | D8: =SUMIFS(Détail!$H$2:$H$929,Détail!$A$2:$A$929,$A8,Détail!$D$2:$D$929,"Aurélie") -> 1445.3 | E8: =SUMIFS(Détail!$I$2:$I$929,Détail!$A$2:$A$929,$A8,Détail!$D$2:$D$929,"Aurélie") -> 95.205
A9: 46300 | B9: =SUMIFS(Détail!$H$2:$H$929,Détail!$A$2:$A$929,$A9,Détail!$D$2:$D$929,"Nicolas") -> 1861.7 | C9: =SUMIFS(Détail!$I$2:$I$929,Détail!$A$2:$A$929,$A9,Détail!$D$2:$D$929,"Nicolas") -> 113.72 | D9: =SUMIFS(Détail!$H$2:$H$929,Détail!$A$2:$A$929,$A9,Détail!$D$2:$D$929,"Aurélie") -> 1340.8 | E9: =SUMIFS(Détail!$I$2:$I$929,Détail!$A$2:$A$929,$A9,Détail!$D$2:$D$929,"Aurélie") -> 95.005
A10: 46301 | B10: =SUMIFS(Détail!$H$2:$H$929,Détail!$A$2:$A$929,$A10,Détail!$D$2:$D$929,"Nicolas") -> 1876.3 | C10: =SUMIFS(Détail!$I$2:$I$929,Détail!$A$2:$A$929,$A10,Détail!$D$2:$D$929,"Nicolas") -> 113.955 | D10: =SUMIFS(Détail!$H$2:$H$929,Détail!$A$2:$A$929,$A10,Détail!$D$2:$D$929,"Aurélie") -> 1300.05 | E10: =SUMIFS(Détail!$I$2:$I$929,Détail!$A$2:$A$929,$A10,Détail!$D$2:$D$929,"Aurélie") -> 92.33
A11: 46302 | B11: =SUMIFS(Détail!$H$2:$H$929,Détail!$A$2:$A$929,$A11,Détail!$D$2:$D$929,"Nicolas") -> 1742.6 | C11: =SUMIFS(Détail!$I$2:$I$929,Détail!$A$2:$A$929,$A11,Détail!$D$2:$D$929,"Nicolas") -> 105.555 | D11: =SUMIFS(Détail!$H$2:$H$929,Détail!$A$2:$A$929,$A11,Détail!$D$2:$D$929,"Aurélie") -> 1233.1 | E11: =SUMIFS(Détail!$I$2:$I$929,Détail!$A$2:$A$929,$A11,Détail!$D$2:$D$929,"Aurélie") -> 89.89
A12: 46303 | B12: =SUMIFS(Détail!$H$2:$H$929,Détail!$A$2:$A$929,$A12,Détail!$D$2:$D$929,"Nicolas") -> 1775.9 | C12: =SUMIFS(Détail!$I$2:$I$929,Détail!$A$2:$A$929,$A12,Détail!$D$2:$D$929,"Nicolas") -> 111.65 | D12: =SUMIFS(Détail!$H$2:$H$929,Détail!$A$2:$A$929,$A12,Détail!$D$2:$D$929,"Aurélie") -> 1283.1 | E12: =SUMIFS(Détail!$I$2:$I$929,Détail!$A$2:$A$929,$A12,Détail!$D$2:$D$929,"Aurélie") -> 95.085
A13: 46304 | B13: =SUMIFS(Détail!$H$2:$H$929,Détail!$A$2:$A$929,$A13,Détail!$D$2:$D$929,"Nicolas") -> 1958.3 | C13: =SUMIFS(Détail!$I$2:$I$929,Détail!$A$2:$A$929,$A13,Détail!$D$2:$D$929,"Nicolas") -> 104.445 | D13: =SUMIFS(Détail!$H$2:$H$929,Détail!$A$2:$A$929,$A13,Détail!$D$2:$D$929,"Aurélie") -> 1476.2 | E13: =SUMIFS(Détail!$I$2:$I$929,Détail!$A$2:$A$929,$A13,Détail!$D$2:$D$929,"Aurélie") -> 92.51
A14: 46305 | B14: =SUMIFS(Détail!$H$2:$H$929,Détail!$A$2:$A$929,$A14,Détail!$D$2:$D$929,"Nicolas") -> 1930.15 | C14: =SUMIFS(Détail!$I$2:$I$929,Détail!$A$2:$A$929,$A14,Détail!$D$2:$D$929,"Nicolas") -> 103.92 | D14: =SUMIFS(Détail!$H$2:$H$929,Détail!$A$2:$A$929,$A14,Détail!$D$2:$D$929,"Aurélie") -> 1470.55 | E14: =SUMIFS(Détail!$I$2:$I$929,Détail!$A$2:$A$929,$A14,Détail!$D$2:$D$929,"Aurélie") -> 90.025
A15: 46306 | B15: =SUMIFS(Détail!$H$2:$H$929,Détail!$A$2:$A$929,$A15,Détail!$D$2:$D$929,"Nicolas") -> 1883.3 | C15: =SUMIFS(Détail!$I$2:$I$929,Détail!$A$2:$A$929,$A15,Détail!$D$2:$D$929,"Nicolas") -> 106.06 | D15: =SUMIFS(Détail!$H$2:$H$929,Détail!$A$2:$A$929,$A15,Détail!$D$2:$D$929,"Aurélie") -> 1415.8 | E15: =SUMIFS(Détail!$I$2:$I$929,Détail!$A$2:$A$929,$A15,Détail!$D$2:$D$929,"Aurélie") -> 88.075
A16: 46307 | B16: =SUMIFS(Détail!$H$2:$H$929,Détail!$A$2:$A$929,$A16,Détail!$D$2:$D$929,"Nicolas") -> 1988.45 | C16: =SUMIFS(Détail!$I$2:$I$929,Détail!$A$2:$A$929,$A16,Détail!$D$2:$D$929,"Nicolas") -> 118.835 | D16: =SUMIFS(Détail!$H$2:$H$929,Détail!$A$2:$A$929,$A16,Détail!$D$2:$D$929,"Aurélie") -> 1488.55 | E16: =SUMIFS(Détail!$I$2:$I$929,Détail!$A$2:$A$929,$A16,Détail!$D$2:$D$929,"Aurélie") -> 100.53
... A25: 46316 | B25: =SUMIFS(Détail!$H$2:$H$929,Détail!$A$2:$A$929,$A25,Détail!$D$2:$D$929,"Nicolas") -> 1842.8 | C25: =SUMIFS(Détail!$I$2:$I$929,Détail!$A$2:$A$929,$A25,Détail!$D$2:$D$929,"Nicolas") -> 98.78 | D25: =SUMIFS(Détail!$H$2:$H$929,Détail!$A$2:$A$929,$A25,Détail!$D$2:$D$929,"Aurélie") -> 1283.9 | E25: =SUMIFS(Détail!$I$2:$I$929,Détail!$A$2:$A$929,$A25,Détail!$D$2:$D$929,"Aurélie") -> 82.145
A27: Moyenne semaine 1 (1-7) | B27: =AVERAGE(B5:B11) -> 1842.1071 | C27: =AVERAGE(C5:C11) -> 106.98857 | D27: =AVERAGE(D5:D11) -> 1317.1286 | E27: =AVERAGE(E5:E11) -> 89.522143
A28: Moyenne semaine 2 (8-14) | B28: =AVERAGE(B12:B18) -> 1900.1786 | C28: =AVERAGE(C12:C18) -> 109.35857 | D28: =AVERAGE(D12:D18) -> 1393.7286 | E28: =AVERAGE(E12:E18) -> 92.397857
A29: Moyenne semaine 3 (15-21) | B29: =AVERAGE(B19:B25) -> 1897.45 | C29: =AVERAGE(C19:C25) -> 108.005 | D29: =AVERAGE(D19:D25) -> 1345.5 | E29: =AVERAGE(E19:E25) -> 90.672143
A30: Moyenne 21 jours | B30: =AVERAGE(B5:B25) -> 1879.9119 | C30: =AVERAGE(C5:C25) -> 108.11738 | D30: =AVERAGE(D5:D25) -> 1352.119 | E30: =AVERAGE(E5:E25) -> 90.864048

Sheet Détail
A1: Date | B1: Repas | C1: Plat | D1: Personne | E1: Aliment | F1: Quantité | G1: Unité | H1: kcal | I1: Protéines (g) | J1: Course | L1: Onglet de calcul : les quantités viennent du Menu (vert = lien). Modifie les quantités dans le Menu, pas ici.
A2: 46296 | B2: Petit-déjeuner | C2: Smoothie + œuf (Nicolas) / œufs, jambon, pain, pomme (Aurélie) | D2: Nicolas | E2: Lait | F2: =Menu!D7 -> 250 | G2: ml | H2: =F2/INDEX(Valeurs!$B$2:$B$40,MATCH(E2,Valeurs!$A$2:$A$40,0))*INDEX(Valeurs!$D$2:$D$40,MATCH(E2,Valeurs!$A$2:$A$40,0)) -> 115 | I2: =F2/INDEX(Valeurs!$B$2:$B$40,MATCH(E2,Valeurs!$A$2:$A$40,0))*INDEX(Valeurs!$E$2:$E$40,MATCH(E2,Valeurs!$A$2:$A$40,0)) -> 8.25 | J2: 1
A3: 46296 | B3: Petit-déjeuner | C3: Smoothie + œuf (Nicolas) / œufs, jambon, pain, pomme (Aurélie) | D3: Aurélie | E3: Lait | F3: =Menu!E7 -> 0 | G3: ml | H3: =F3/INDEX(Valeurs!$B$2:$B$40,MATCH(E3,Valeurs!$A$2:$A$40,0))*INDEX(Valeurs!$D$2:$D$40,MATCH(E3,Valeurs!$A$2:$A$40,0)) -> 0 | I3: =F3/INDEX(Valeurs!$B$2:$B$40,MATCH(E3,Valeurs!$A$2:$A$40,0))*INDEX(Valeurs!$E$2:$E$40,MATCH(E3,Valeurs!$A$2:$A$40,0)) -> 0 | J3: 1
A4: 46296 | B4: Petit-déjeuner | C4: Smoothie + œuf (Nicolas) / œufs, jambon, pain, pomme (Aurélie) | D4: Nicolas | E4: Bananes | F4: =Menu!D8 -> 100 | G4: g | H4: =F4/INDEX(Valeurs!$B$2:$B$40,MATCH(E4,Valeurs!$A$2:$A$40,0))*INDEX(Valeurs!$D$2:$D$40,MATCH(E4,Valeurs!$A$2:$A$40,0)) -> 90 | I4: =F4/INDEX(Valeurs!$B$2:$B$40,MATCH(E4,Valeurs!$A$2:$A$40,0))*INDEX(Valeurs!$E$2:$E$40,MATCH(E4,Valeurs!$A$2:$A$40,0)) -> 1.1 | J4: 1
A5: 46296 | B5: Petit-déjeuner | C5: Smoothie + œuf (Nicolas) / œufs, jambon, pain, pomme (Aurélie) | D5: Aurélie | E5: Bananes | F5: =Menu!E8 -> 0 | G5: g | H5: =F5/INDEX(Valeurs!$B$2:$B$40,MATCH(E5,Valeurs!$A$2:$A$40,0))*INDEX(Valeurs!$D$2:$D$40,MATCH(E5,Valeurs!$A$2:$A$40,0)) -> 0 | I5: =F5/INDEX(Valeurs!$B$2:$B$40,MATCH(E5,Valeurs!$A$2:$A$40,0))*INDEX(Valeurs!$E$2:$E$40,MATCH(E5,Valeurs!$A$2:$A$40,0)) -> 0 | J5: 1
A6: 46296 | B6: Petit-déjeuner | C6: Smoothie + œuf (Nicolas) / œufs, jambon, pain, pomme (Aurélie) | D6: Nicolas | E6: Flocons d'avoine | F6: =Menu!D9 -> 65 | G6: g | H6: =F6/INDEX(Valeurs!$B$2:$B$40,MATCH(E6,Valeurs!$A$2:$A$40,0))*INDEX(Valeurs!$D$2:$D$40,MATCH(E6,Valeurs!$A$2:$A$40,0)) -> 241.8 | I6: =F6/INDEX(Valeurs!$B$2:$B$40,MATCH(E6,Valeurs!$A$2:$A$40,0))*INDEX(Valeurs!$E$2:$E$40,MATCH(E6,Valeurs!$A$2:$A$40,0)) -> 8.775 | J6: 1
A7: 46296 | B7: Petit-déjeuner | C7: Smoothie + œuf (Nicolas) / œufs, jambon, pain, pomme (Aurélie) | D7: Aurélie | E7: Flocons d'avoine | F7: =Menu!E9 -> 0 | G7: g | H7: =F7/INDEX(Valeurs!$B$2:$B$40,MATCH(E7,Valeurs!$A$2:$A$40,0))*INDEX(Valeurs!$D$2:$D$40,MATCH(E7,Valeurs!$A$2:$A$40,0)) -> 0 | I7: =F7/INDEX(Valeurs!$B$2:$B$40,MATCH(E7,Valeurs!$A$2:$A$40,0))*INDEX(Valeurs!$E$2:$E$40,MATCH(E7,Valeurs!$A$2:$A$40,0)) -> 0 | J7: 1
A8: 46296 | B8: Petit-déjeuner | C8: Smoothie + œuf (Nicolas) / œufs, jambon, pain, pomme (Aurélie) | D8: Nicolas | E8: Œufs | F8: =Menu!D10 -> 1 | G8: unité | H8: =F8/INDEX(Valeurs!$B$2:$B$40,MATCH(E8,Valeurs!$A$2:$A$40,0))*INDEX(Valeurs!$D$2:$D$40,MATCH(E8,Valeurs!$A$2:$A$40,0)) -> 87 | I8: =F8/INDEX(Valeurs!$B$2:$B$40,MATCH(E8,Valeurs!$A$2:$A$40,0))*INDEX(Valeurs!$E$2:$E$40,MATCH(E8,Valeurs!$A$2:$A$40,0)) -> 7.5 | J8: 1
A9: 46296 | B9: Petit-déjeuner | C9: Smoothie + œuf (Nicolas) / œufs, jambon, pain, pomme (Aurélie) | D9: Aurélie | E9: Œufs | F9: =Menu!E10 -> 2 | G9: unité | H9: =F9/INDEX(Valeurs!$B$2:$B$40,MATCH(E9,Valeurs!$A$2:$A$40,0))*INDEX(Valeurs!$D$2:$D$40,MATCH(E9,Valeurs!$A$2:$A$40,0)) -> 174 | I9: =F9/INDEX(Valeurs!$B$2:$B$40,MATCH(E9,Valeurs!$A$2:$A$40,0))*INDEX(Valeurs!$E$2:$E$40,MATCH(E9,Valeurs!$A$2:$A$40,0)) -> 15 | J9: 1
A10: 46296 | B10: Petit-déjeuner | C10: Smoothie + œuf (Nicolas) / œufs, jambon, pain, pomme (Aurélie) | D10: Nicolas | E10: Jambon | F10: =Menu!D11 -> 0 | G10: g | H10: =F10/INDEX(Valeurs!$B$2:$B$40,MATCH(E10,Valeurs!$A$2:$A$40,0))*INDEX(Valeurs!$D$2:$D$40,MATCH(E10,Valeurs!$A$2:$A$40,0)) -> 0 | I10: =F10/INDEX(Valeurs!$B$2:$B$40,MATCH(E10,Valeurs!$A$2:$A$40,0))*INDEX(Valeurs!$E$2:$E$40,MATCH(E10,Valeurs!$A$2:$A$40,0)) -> 0 | J10: 1
A11: 46296 | B11: Petit-déjeuner | C11: Smoothie + œuf (Nicolas) / œufs, jambon, pain, pomme (Aurélie) | D11: Aurélie | E11: Jambon | F11: =Menu!E11 -> 30 | G11: g | H11: =F11/INDEX(Valeurs!$B$2:$B$40,MATCH(E11,Valeurs!$A$2:$A$40,0))*INDEX(Valeurs!$D$2:$D$40,MATCH(E11,Valeurs!$A$2:$A$40,0)) -> 33 | I11: =F11/INDEX(Valeurs!$B$2:$B$40,MATCH(E11,Valeurs!$A$2:$A$40,0))*INDEX(Valeurs!$E$2:$E$40,MATCH(E11,Valeurs!$A$2:$A$40,0)) -> 6 | J11: 1
A12: 46296 | B12: Petit-déjeuner | C12: Smoothie + œuf (Nicolas) / œufs, jambon, pain, pomme (Aurélie) | D12: Nicolas | E12: Tomates | F12: =Menu!D12 -> 0 | G12: g | H12: =F12/INDEX(Valeurs!$B$2:$B$40,MATCH(E12,Valeurs!$A$2:$A$40,0))*INDEX(Valeurs!$D$2:$D$40,MATCH(E12,Valeurs!$A$2:$A$40,0)) -> 0 | I12: =F12/INDEX(Valeurs!$B$2:$B$40,MATCH(E12,Valeurs!$A$2:$A$40,0))*INDEX(Valeurs!$E$2:$E$40,MATCH(E12,Valeurs!$A$2:$A$40,0)) -> 0 | J12: 1
A13: 46296 | B13: Petit-déjeuner | C13: Smoothie + œuf (Nicolas) / œufs, jambon, pain, pomme (Aurélie) | D13: Aurélie | E13: Tomates | F13: =Menu!E12 -> 80 | G13: g | H13: =F13/INDEX(Valeurs!$B$2:$B$40,MATCH(E13,Valeurs!$A$2:$A$40,0))*INDEX(Valeurs!$D$2:$D$40,MATCH(E13,Valeurs!$A$2:$A$40,0)) -> 14.4 | I13: =F13/INDEX(Valeurs!$B$2:$B$40,MATCH(E13,Valeurs!$A$2:$A$40,0))*INDEX(Valeurs!$E$2:$E$40,MATCH(E13,Valeurs!$A$2:$A$40,0)) -> 0.72 | J13: 1
A14: 46296 | B14: Petit-déjeuner | C14: Smoothie + œuf (Nicolas) / œufs, jambon, pain, pomme (Aurélie) | D14: Nicolas | E14: Pain complet | F14: =Menu!D13 -> 0 | G14: g | H14: =F14/INDEX(Valeurs!$B$2:$B$40,MATCH(E14,Valeurs!$A$2:$A$40,0))*INDEX(Valeurs!$D$2:$D$40,MATCH(E14,Valeurs!$A$2:$A$40,0)) -> 0 | I14: =F14/INDEX(Valeurs!$B$2:$B$40,MATCH(E14,Valeurs!$A$2:$A$40,0))*INDEX(Valeurs!$E$2:$E$40,MATCH(E14,Valeurs!$A$2:$A$40,0)) -> 0 | J14: 1
A15: 46296 | B15: Petit-déjeuner | C15: Smoothie + œuf (Nicolas) / œufs, jambon, pain, pomme (Aurélie) | D15: Aurélie | E15: Pain complet | F15: =Menu!E13 -> 40 | G15: g | H15: =F15/INDEX(Valeurs!$B$2:$B$40,MATCH(E15,Valeurs!$A$2:$A$40,0))*INDEX(Valeurs!$D$2:$D$40,MATCH(E15,Valeurs!$A$2:$A$40,0)) -> 96 | I15: =F15/INDEX(Valeurs!$B$2:$B$40,MATCH(E15,Valeurs!$A$2:$A$40,0))*INDEX(Valeurs!$E$2:$E$40,MATCH(E15,Valeurs!$A$2:$A$40,0)) -> 3.6 | J15: 1
A16: 46296 | B16: Petit-déjeuner | C16: Smoothie + œuf (Nicolas) / œufs, jambon, pain, pomme (Aurélie) | D16: Nicolas | E16: Pommes | F16: =Menu!D14 -> 0 | G16: g | H16: =F16/INDEX(Valeurs!$B$2:$B$40,MATCH(E16,Valeurs!$A$2:$A$40,0))*INDEX(Valeurs!$D$2:$D$40,MATCH(E16,Valeurs!$A$2:$A$40,0)) -> 0 | I16: =F16/INDEX(Valeurs!$B$2:$B$40,MATCH(E16,Valeurs!$A$2:$A$40,0))*INDEX(Valeurs!$E$2:$E$40,MATCH(E16,Valeurs!$A$2:$A$40,0)) -> 0 | J16: 1
A17: 46296 | B17: Petit-déjeuner | C17: Smoothie + œuf (Nicolas) / œufs, jambon, pain, pomme (Aurélie) | D17: Aurélie | E17: Pommes | F17: =Menu!E14 -> 150 | G17: g | H17: =F17/INDEX(Valeurs!$B$2:$B$40,MATCH(E17,Valeurs!$A$2:$A$40,0))*INDEX(Valeurs!$D$2:$D$40,MATCH(E17,Valeurs!$A$2:$A$40,0)) -> 78 | I17: =F17/INDEX(Valeurs!$B$2:$B$40,MATCH(E17,Valeurs!$A$2:$A$40,0))*INDEX(Valeurs!$E$2:$E$40,MATCH(E17,Valeurs!$A$2:$A$40,0)) -> 0.45 | J17: 1
A18: 46296 | B18: Déjeuner | C18: Poulet rôti, pommes de terre, haricots verts | D18: Nicolas | E18: Poulet | F18: =Menu!D15 -> 150 | G18: g | H18: =F18/INDEX(Valeurs!$B$2:$B$40,MATCH(E18,Valeurs!$A$2:$A$40,0))*INDEX(Valeurs!$D$2:$D$40,MATCH(E18,Valeurs!$A$2:$A$40,0)) -> 172.5 | I18: =F18/INDEX(Valeurs!$B$2:$B$40,MATCH(E18,Valeurs!$A$2:$A$40,0))*INDEX(Valeurs!$E$2:$E$40,MATCH(E18,Valeurs!$A$2:$A$40,0)) -> 34.5 | J18: 1
A19: 46296 | B19: Déjeuner | C19: Poulet rôti, pommes de terre, haricots verts | D19: Aurélie | E19: Poulet | F19: =Menu!E15 -> 120 | G19: g | H19: =F19/INDEX(Valeurs!$B$2:$B$40,MATCH(E19,Valeurs!$A$2:$A$40,0))*INDEX(Valeurs!$D$2:$D$40,MATCH(E19,Valeurs!$A$2:$A$40,0)) -> 138 | I19: =F19/INDEX(Valeurs!$B$2:$B$40,MATCH(E19,Valeurs!$A$2:$A$40,0))*INDEX(Valeurs!$E$2:$E$40,MATCH(E19,Valeurs!$A$2:$A$40,0)) -> 27.6 | J19: 1
A20: 46296 | B20: Déjeuner | C20: Poulet rôti, pommes de terre, haricots verts | D20: Nicolas | E20: Pommes de terre | F20: =Menu!D16 -> 360 | G20: g | H20: =F20/INDEX(Valeurs!$B$2:$B$40,MATCH(E20,Valeurs!$A$2:$A$40,0))*INDEX(Valeurs!$D$2:$D$40,MATCH(E20,Valeurs!$A$2:$A$40,0)) -> 288 | I20: =F20/INDEX(Valeurs!$B$2:$B$40,MATCH(E20,Valeurs!$A$2:$A$40,0))*INDEX(Valeurs!$E$2:$E$40,MATCH(E20,Valeurs!$A$2:$A$40,0)) -> 7.2 | J20: 1
A21: 46296 | B21: Déjeuner | C21: Poulet rôti, pommes de terre, haricots verts | D21: Aurélie | E21: Pommes de terre | F21: =Menu!E16 -> 170 | G21: g | H21: =F21/INDEX(Valeurs!$B$2:$B$40,MATCH(E21,Valeurs!$A$2:$A$40,0))*INDEX(Valeurs!$D$2:$D$40,MATCH(E21,Valeurs!$A$2:$A$40,0)) -> 136 | I21: =F21/INDEX(Valeurs!$B$2:$B$40,MATCH(E21,Valeurs!$A$2:$A$40,0))*INDEX(Valeurs!$E$2:$E$40,MATCH(E21,Valeurs!$A$2:$A$40,0)) -> 3.4 | J21: 1
A22: 46296 | B22: Déjeuner | C22: Poulet rôti, pommes de terre, haricots verts | D22: Nicolas | E22: Haricots verts | F22: =Menu!D17 -> 250 | G22: g | H22: =F22/INDEX(Valeurs!$B$2:$B$40,MATCH(E22,Valeurs!$A$2:$A$40,0))*INDEX(Valeurs!$D$2:$D$40,MATCH(E22,Valeurs!$A$2:$A$40,0)) -> 77.5 | I22: =F22/INDEX(Valeurs!$B$2:$B$40,MATCH(E22,Valeurs!$A$2:$A$40,0))*INDEX(Valeurs!$E$2:$E$40,MATCH(E22,Valeurs!$A$2:$A$40,0)) -> 4.5 | J22: 1
A23: 46296 | B23: Déjeuner | C23: Poulet rôti, pommes de terre, haricots verts | D23: Aurélie | E23: Haricots verts | F23: =Menu!E17 -> 280 | G23: g | H23: =F23/INDEX(Valeurs!$B$2:$B$40,MATCH(E23,Valeurs!$A$2:$A$40,0))*INDEX(Valeurs!$D$2:$D$40,MATCH(E23,Valeurs!$A$2:$A$40,0)) -> 86.8 | I23: =F23/INDEX(Valeurs!$B$2:$B$40,MATCH(E23,Valeurs!$A$2:$A$40,0))*INDEX(Valeurs!$E$2:$E$40,MATCH(E23,Valeurs!$A$2:$A$40,0)) -> 5.04 | J23: 1
A24: 46296 | B24: Déjeuner | C24: Poulet rôti, pommes de terre, haricots verts | D24: Nicolas | E24: Huile | F24: =Menu!D18 -> 10 | G24: g | H24: =F24/INDEX(Valeurs!$B$2:$B$40,MATCH(E24,Valeurs!$A$2:$A$40,0))*INDEX(Valeurs!$D$2:$D$40,MATCH(E24,Valeurs!$A$2:$A$40,0)) -> 90 | I24: =F24/INDEX(Valeurs!$B$2:$B$40,MATCH(E24,Valeurs!$A$2:$A$40,0))*INDEX(Valeurs!$E$2:$E$40,MATCH(E24,Valeurs!$A$2:$A$40,0)) -> 0 | J24: 1
A25: 46296 | B25: Déjeuner | C25: Poulet rôti, pommes de terre, haricots verts | D25: Aurélie | E25: Huile | F25: =Menu!E18 -> 7 | G25: g | H25: =F25/INDEX(Valeurs!$B$2:$B$40,MATCH(E25,Valeurs!$A$2:$A$40,0))*INDEX(Valeurs!$D$2:$D$40,MATCH(E25,Valeurs!$A$2:$A$40,0)) -> 63 | I25: =F25/INDEX(Valeurs!$B$2:$B$40,MATCH(E25,Valeurs!$A$2:$A$40,0))*INDEX(Valeurs!$E$2:$E$40,MATCH(E25,Valeurs!$A$2:$A$40,0)) -> 0 | J25: 1
A26: 46296 | B26: Dîner | C26: Poisson blanc, patate douce, poêlée courgettes-poivrons | D26: Nicolas | E26: Poisson blanc | F26: =Menu!D19 -> 150 | G26: g | H26: =F26/INDEX(Valeurs!$B$2:$B$40,MATCH(E26,Valeurs!$A$2:$A$40,0))*INDEX(Valeurs!$D$2:$D$40,MATCH(E26,Valeurs!$A$2:$A$40,0)) -> 120 | I26: =F26/INDEX(Valeurs!$B$2:$B$40,MATCH(E26,Valeurs!$A$2:$A$40,0))*INDEX(Valeurs!$E$2:$E$40,MATCH(E26,Valeurs!$A$2:$A$40,0)) -> 25.5 | J26: 1
A27: 46296 | B27: Dîner | C27: Poisson blanc, patate douce, poêlée courgettes-poivrons | D27: Aurélie | E27: Poisson blanc | F27: =Menu!E19 -> 125 | G27: g | H27: =F27/INDEX(Valeurs!$B$2:$B$40,MATCH(E27,Valeurs!$A$2:$A$40,0))*INDEX(Valeurs!$D$2:$D$40,MATCH(E27,Valeurs!$A$2:$A$40,0)) -> 100 | I27: =F27/INDEX(Valeurs!$B$2:$B$40,MATCH(E27,Valeurs!$A$2:$A$40,0))*INDEX(Valeurs!$E$2:$E$40,MATCH(E27,Valeurs!$A$2:$A$40,0)) -> 21.25 | J27: 1
A28: 46296 | B28: Dîner | C28: Poisson blanc, patate douce, poêlée courgettes-poivrons | D28: Nicolas | E28: Patates douces | F28: =Menu!D20 -> 300 | G28: g | H28: =F28/INDEX(Valeurs!$B$2:$B$40,MATCH(E28,Valeurs!$A$2:$A$40,0))*INDEX(Valeurs!$D$2:$D$40,MATCH(E28,Valeurs!$A$2:$A$40,0)) -> 258 | I28: =F28/INDEX(Valeurs!$B$2:$B$40,MATCH(E28,Valeurs!$A$2:$A$40,0))*INDEX(Valeurs!$E$2:$E$40,MATCH(E28,Valeurs!$A$2:$A$40,0)) -> 4.8 | J28: 1
A29: 46296 | B29: Dîner | C29: Poisson blanc, patate douce, poêlée courgettes-poivrons | D29: Aurélie | E29: Patates douces | F29: =Menu!E20 -> 140 | G29: g | H29: =F29/INDEX(Valeurs!$B$2:$B$40,MATCH(E29,Valeurs!$A$2:$A$40,0))*INDEX(Valeurs!$D$2:$D$40,MATCH(E29,Valeurs!$A$2:$A$40,0)) -> 120.4 | I29: =F29/INDEX(Valeurs!$B$2:$B$40,MATCH(E29,Valeurs!$A$2:$A$40,0))*INDEX(Valeurs!$E$2:$E$40,MATCH(E29,Valeurs!$A$2:$A$40,0)) -> 2.24 | J29: 1
A30: 46296 | B30: Dîner | C30: Poisson blanc, patate douce, poêlée courgettes-poivrons | D30: Nicolas | E30: Courgettes | F30: =Menu!D21 -> 170 | G30: g | H30: =F30/INDEX(Valeurs!$B$2:$B$40,MATCH(E30,Valeurs!$A$2:$A$40,0))*INDEX(Valeurs!$D$2:$D$40,MATCH(E30,Valeurs!$A$2:$A$40,0)) -> 28.9 | I30: =F30/INDEX(Valeurs!$B$2:$B$40,MATCH(E30,Valeurs!$A$2:$A$40,0))*INDEX(Valeurs!$E$2:$E$40,MATCH(E30,Valeurs!$A$2:$A$40,0)) -> 2.04 | J30: 1
A31: 46296 | B31: Dîner | C31: Poisson blanc, patate douce, poêlée courgettes-poivrons | D31: Aurélie | E31: Courgettes | F31: =Menu!E21 -> 200 | G31: g | H31: =F31/INDEX(Valeurs!$B$2:$B$40,MATCH(E31,Valeurs!$A$2:$A$40,0))*INDEX(Valeurs!$D$2:$D$40,MATCH(E31,Valeurs!$A$2:$A$40,0)) -> 34 | I31: =F31/INDEX(Valeurs!$B$2:$B$40,MATCH(E31,Valeurs!$A$2:$A$40,0))*INDEX(Valeurs!$E$2:$E$40,MATCH(E31,Valeurs!$A$2:$A$40,0)) -> 2.4 | J31: 1
A32: 46296 | B32: Dîner | C32: Poisson blanc, patate douce, poêlée courgettes-poivrons | D32: Nicolas | E32: Poivrons | F32: =Menu!D22 -> 50 | G32: g | H32: =F32/INDEX(Valeurs!$B$2:$B$40,MATCH(E32,Valeurs!$A$2:$A$40,0))*INDEX(Valeurs!$D$2:$D$40,MATCH(E32,Valeurs!$A$2:$A$40,0)) -> 13.5 | I32: =F32/INDEX(Valeurs!$B$2:$B$40,MATCH(E32,Valeurs!$A$2:$A$40,0))*INDEX(Valeurs!$E$2:$E$40,MATCH(E32,Valeurs!$A$2:$A$40,0)) -> 0.5 | J32: 1
A33: 46296 | B33: Dîner | C33: Poisson blanc, patate douce, poêlée courgettes-poivrons | D33: Aurélie | E33: Poivrons | F33: =Menu!E22 -> 60 | G33: g | H33: =F33/INDEX(Valeurs!$B$2:$B$40,MATCH(E33,Valeurs!$A$2:$A$40,0))*INDEX(Valeurs!$D$2:$D$40,MATCH(E33,Valeurs!$A$2:$A$40,0)) -> 16.2 | I33: =F33/INDEX(Valeurs!$B$2:$B$40,MATCH(E33,Valeurs!$A$2:$A$40,0))*INDEX(Valeurs!$E$2:$E$40,MATCH(E33,Valeurs!$A$2:$A$40,0)) -> 0.6 | J33: 1
A34: 46296 | B34: Dîner | C34: Poisson blanc, patate douce, poêlée courgettes-poivrons | D34: Nicolas | E34: Oignons | F34: =Menu!D23 -> 20 | G34: g | H34: =F34/INDEX(Valeurs!$B$2:$B$40,MATCH(E34,Valeurs!$A$2:$A$40,0))*INDEX(Valeurs!$D$2:$D$40,MATCH(E34,Valeurs!$A$2:$A$40,0)) -> 8 | I34: =F34/INDEX(Valeurs!$B$2:$B$40,MATCH(E34,Valeurs!$A$2:$A$40,0))*INDEX(Valeurs!$E$2:$E$40,MATCH(E34,Valeurs!$A$2:$A$40,0)) -> 0.22 | J34: 1
A35: 46296 | B35: Dîner | C35: Poisson blanc, patate douce, poêlée courgettes-poivrons | D35: Aurélie | E35: Oignons | F35: =Menu!E23 -> 20 | G35: g | H35: =F35/INDEX(Valeurs!$B$2:$B$40,MATCH(E35,Valeurs!$A$2:$A$40,0))*INDEX(Valeurs!$D$2:$D$40,MATCH(E35,Valeurs!$A$2:$A$40,0)) -> 8 | I35: =F35/INDEX(Valeurs!$B$2:$B$40,MATCH(E35,Valeurs!$A$2:$A$40,0))*INDEX(Valeurs!$E$2:$E$40,MATCH(E35,Valeurs!$A$2:$A$40,0)) -> 0.22 | J35: 1
A36: 46296 | B36: Dîner | C36: Poisson blanc, patate douce, poêlée courgettes-poivrons | D36: Nicolas | E36: Huile | F36: =Menu!D24 -> 10 | G36: g | H36: =F36/INDEX(Valeurs!$B$2:$B$40,MATCH(E36,Valeurs!$A$2:$A$40,0))*INDEX(Valeurs!$D$2:$D$40,MATCH(E36,Valeurs!$A$2:$A$40,0)) -> 90 | I36: =F36/INDEX(Valeurs!$B$2:$B$40,MATCH(E36,Valeurs!$A$2:$A$40,0))*INDEX(Valeurs!$E$2:$E$40,MATCH(E36,Valeurs!$A$2:$A$40,0)) -> 0 | J36: 1
A37: 46296 | B37: Dîner | C37: Poisson blanc, patate douce, poêlée courgettes-poivrons | D37: Aurélie | E37: Huile | F37: =Menu!E24 -> 7 | G37: g | H37: =F37/INDEX(Valeurs!$B$2:$B$40,MATCH(E37,Valeurs!$A$2:$A$40,0))*INDEX(Valeurs!$D$2:$D$40,MATCH(E37,Valeurs!$A$2:$A$40,0)) -> 63 | I37: =F37/INDEX(Valeurs!$B$2:$B$40,MATCH(E37,Valeurs!$A$2:$A$40,0))*INDEX(Valeurs!$E$2:$E$40,MATCH(E37,Valeurs!$A$2:$A$40,0)) -> 0 | J37: 1
A38: 46296 | B38: Dessert | C38: Yaourt + chocolat | D38: Nicolas | E38: Yaourt nature | F38: =Menu!D25 -> 125 | G38: g | H38: =F38/INDEX(Valeurs!$B$2:$B$40,MATCH(E38,Valeurs!$A$2:$A$40,0))*INDEX(Valeurs!$D$2:$D$40,MATCH(E38,Valeurs!$A$2:$A$40,0)) -> 75 | I38: =F38/INDEX(Valeurs!$B$2:$B$40,MATCH(E38,Valeurs!$A$2:$A$40,0))*INDEX(Valeurs!$E$2:$E$40,MATCH(E38,Valeurs!$A$2:$A$40,0)) -> 5.625 | J38: 1
A39: 46296 | B39: Dessert | C39: Yaourt + chocolat | D39: Aurélie | E39: Yaourt nature | F39: =Menu!E25 -> 125 | G39: g | H39: =F39/INDEX(Valeurs!$B$2:$B$40,MATCH(E39,Valeurs!$A$2:$A$40,0))*INDEX(Valeurs!$D$2:$D$40,MATCH(E39,Valeurs!$A$2:$A$40,0)) -> 75 | I39: =F39/INDEX(Valeurs!$B$2:$B$40,MATCH(E39,Valeurs!$A$2:$A$40,0))*INDEX(Valeurs!$E$2:$E$40,MATCH(E39,Valeurs!$A$2:$A$40,0)) -> 5.625 | J39: 1
A40: 46296 | B40: Dessert | C40: Yaourt + chocolat | D40: Nicolas | E40: Chocolat noir | F40: =Menu!D26 -> 10 | G40: g | H40: =F40/INDEX(Valeurs!$B$2:$B$40,MATCH(E40,Valeurs!$A$2:$A$40,0))*INDEX(Valeurs!$D$2:$D$40,MATCH(E40,Valeurs!$A$2:$A$40,0)) -> 58 | I40: =F40/INDEX(Valeurs!$B$2:$B$40,MATCH(E40,Valeurs!$A$2:$A$40,0))*INDEX(Valeurs!$E$2:$E$40,MATCH(E40,Valeurs!$A$2:$A$40,0)) -> 0.75 | J40: 1
A41: 46296 | B41: Dessert | C41: Yaourt + chocolat | D41: Aurélie | E41: Chocolat noir | F41: =Menu!E26 -> 10 | G41: g | H41: =F41/INDEX(Valeurs!$B$2:$B$40,MATCH(E41,Valeurs!$A$2:$A$40,0))*INDEX(Valeurs!$D$2:$D$40,MATCH(E41,Valeurs!$A$2:$A$40,0)) -> 58 | I41: =F41/INDEX(Valeurs!$B$2:$B$40,MATCH(E41,Valeurs!$A$2:$A$40,0))*INDEX(Valeurs!$E$2:$E$40,MATCH(E41,Valeurs!$A$2:$A$40,0)) -> 0.75 | J41: 1
A42: 46297 | B42: Petit-déjeuner | C42: Smoothie + œuf (Nicolas) / œufs, jambon, pain, pomme (Aurélie) | D42: Nicolas | E42: Lait | F42: =Menu!D29 -> 250 | G42: ml | H42: =F42/INDEX(Valeurs!$B$2:$B$40,MATCH(E42,Valeurs!$A$2:$A$40,0))*INDEX(Valeurs!$D$2:$D$40,MATCH(E42,Valeurs!$A$2:$A$40,0)) -> 115 | I42: =F42/INDEX(Valeurs!$B$2:$B$40,MATCH(E42,Valeurs!$A$2:$A$40,0))*INDEX(Valeurs!$E$2:$E$40,MATCH(E42,Valeurs!$A$2:$A$40,0)) -> 8.25 | J42: 1
A43: 46297 | B43: Petit-déjeuner | C43: Smoothie + œuf (Nicolas) / œufs, jambon, pain, pomme (Aurélie) | D43: Aurélie | E43: Lait | F43: =Menu!E29 -> 0 | G43: ml | H43: =F43/INDEX(Valeurs!$B$2:$B$40,MATCH(E43,Valeurs!$A$2:$A$40,0))*INDEX(Valeurs!$D$2:$D$40,MATCH(E43,Valeurs!$A$2:$A$40,0)) -> 0 | I43: =F43/INDEX(Valeurs!$B$2:$B$40,MATCH(E43,Valeurs!$A$2:$A$40,0))*INDEX(Valeurs!$E$2:$E$40,MATCH(E43,Valeurs!$A$2:$A$40,0)) -> 0 | J43: 1
A44: 46297 | B44: Petit-déjeuner | C44: Smoothie + œuf (Nicolas) / œufs, jambon, pain, pomme (Aurélie) | D44: Nicolas | E44: Bananes | F44: =Menu!D30 -> 100 | G44: g | H44: =F44/INDEX(Valeurs!$B$2:$B$40,MATCH(E44,Valeurs!$A$2:$A$40,0))*INDEX(Valeurs!$D$2:$D$40,MATCH(E44,Valeurs!$A$2:$A$40,0)) -> 90 | I44: =F44/INDEX(Valeurs!$B$2:$B$40,MATCH(E44,Valeurs!$A$2:$A$40,0))*INDEX(Valeurs!$E$2:$E$40,MATCH(E44,Valeurs!$A$2:$A$40,0)) -> 1.1 | J44: 1
A45: 46297 | B45: Petit-déjeuner | C45: Smoothie + œuf (Nicolas) / œufs, jambon, pain, pomme (Aurélie) | D45: Aurélie | E45: Bananes | F45: =Menu!E30 -> 0 | G45: g | H45: =F45/INDEX(Valeurs!$B$2:$B$40,MATCH(E45,Valeurs!$A$2:$A$40,0))*INDEX(Valeurs!$D$2:$D$40,MATCH(E45,Valeurs!$A$2:$A$40,0)) -> 0 | I45: =F45/INDEX(Valeurs!$B$2:$B$40,MATCH(E45,Valeurs!$A$2:$A$40,0))*INDEX(Valeurs!$E$2:$E$40,MATCH(E45,Valeurs!$A$2:$A$40,0)) -> 0 | J45: 1
A46: 46297 | B46: Petit-déjeuner | C46: Smoothie + œuf (Nicolas) / œufs, jambon, pain, pomme (Aurélie) | D46: Nicolas | E46: Flocons d'avoine | F46: =Menu!D31 -> 65 | G46: g | H46: =F46/INDEX(Valeurs!$B$2:$B$40,MATCH(E46,Valeurs!$A$2:$A$40,0))*INDEX(Valeurs!$D$2:$D$40,MATCH(E46,Valeurs!$A$2:$A$40,0)) -> 241.8 | I46: =F46/INDEX(Valeurs!$B$2:$B$40,MATCH(E46,Valeurs!$A$2:$A$40,0))*INDEX(Valeurs!$E$2:$E$40,MATCH(E46,Valeurs!$A$2:$A$40,0)) -> 8.775 | J46: 1
A47: 46297 | B47: Petit-déjeuner | C47: Smoothie + œuf (Nicolas) / œufs, jambon, pain, pomme (Aurélie) | D47: Aurélie | E47: Flocons d'avoine | F47: =Menu!E31 -> 0 | G47: g | H47: =F47/INDEX(Valeurs!$B$2:$B$40,MATCH(E47,Valeurs!$A$2:$A$40,0))*INDEX(Valeurs!$D$2:$D$40,MATCH(E47,Valeurs!$A$2:$A$40,0)) -> 0 | I47: =F47/INDEX(Valeurs!$B$2:$B$40,MATCH(E47,Valeurs!$A$2:$A$40,0))*INDEX(Valeurs!$E$2:$E$40,MATCH(E47,Valeurs!$A$2:$A$40,0)) -> 0 | J47: 1
A48: 46297 | B48: Petit-déjeuner | C48: Smoothie + œuf (Nicolas) / œufs, jambon, pain, pomme (Aurélie) | D48: Nicolas | E48: Œufs | F48: =Menu!D32 -> 1 | G48: unité | H48: =F48/INDEX(Valeurs!$B$2:$B$40,MATCH(E48,Valeurs!$A$2:$A$40,0))*INDEX(Valeurs!$D$2:$D$40,MATCH(E48,Valeurs!$A$2:$A$40,0)) -> 87 | I48: =F48/INDEX(Valeurs!$B$2:$B$40,MATCH(E48,Valeurs!$A$2:$A$40,0))*INDEX(Valeurs!$E$2:$E$40,MATCH(E48,Valeurs!$A$2:$A$40,0)) -> 7.5 | J48: 1
A49: 46297 | B49: Petit-déjeuner | C49: Smoothie + œuf (Nicolas) / œufs, jambon, pain, pomme (Aurélie) | D49: Aurélie | E49: Œufs | F49: =Menu!E32 -> 2 | G49: unité | H49: =F49/INDEX(Valeurs!$B$2:$B$40,MATCH(E49,Valeurs!$A$2:$A$40,0))*INDEX(Valeurs!$D$2:$D$40,MATCH(E49,Valeurs!$A$2:$A$40,0)) -> 174 | I49: =F49/INDEX(Valeurs!$B$2:$B$40,MATCH(E49,Valeurs!$A$2:$A$40,0))*INDEX(Valeurs!$E$2:$E$40,MATCH(E49,Valeurs!$A$2:$A$40,0)) -> 15 | J49: 1
A50: 46297 | B50: Petit-déjeuner | C50: Smoothie + œuf (Nicolas) / œufs, jambon, pain, pomme (Aurélie) | D50: Nicolas | E50: Jambon | F50: =Menu!D33 -> 0 | G50: g | H50: =F50/INDEX(Valeurs!$B$2:$B$40,MATCH(E50,Valeurs!$A$2:$A$40,0))*INDEX(Valeurs!$D$2:$D$40,MATCH(E50,Valeurs!$A$2:$A$40,0)) -> 0 | I50: =F50/INDEX(Valeurs!$B$2:$B$40,MATCH(E50,Valeurs!$A$2:$A$40,0))*INDEX(Valeurs!$E$2:$E$40,MATCH(E50,Valeurs!$A$2:$A$40,0)) -> 0 | J50: 1
A51: 46297 | B51: Petit-déjeuner | C51: Smoothie + œuf (Nicolas) / œufs, jambon, pain, pomme (Aurélie) | D51: Aurélie | E51: Jambon | F51: =Menu!E33 -> 30 | G51: g | H51: =F51/INDEX(Valeurs!$B$2:$B$40,MATCH(E51,Valeurs!$A$2:$A$40,0))*INDEX(Valeurs!$D$2:$D$40,MATCH(E51,Valeurs!$A$2:$A$40,0)) -> 33 | I51: =F51/INDEX(Valeurs!$B$2:$B$40,MATCH(E51,Valeurs!$A$2:$A$40,0))*INDEX(Valeurs!$E$2:$E$40,MATCH(E51,Valeurs!$A$2:$A$40,0)) -> 6 | J51: 1
A52: 46297 | B52: Petit-déjeuner | C52: Smoothie + œuf (Nicolas) / œufs, jambon, pain, pomme (Aurélie) | D52: Nicolas | E52: Tomates | F52: =Menu!D34 -> 0 | G52: g | H52: =F52/INDEX(Valeurs!$B$2:$B$40,MATCH(E52,Valeurs!$A$2:$A$40,0))*INDEX(Valeurs!$D$2:$D$40,MATCH(E52,Valeurs!$A$2:$A$40,0)) -> 0 | I52: =F52/INDEX(Valeurs!$B$2:$B$40,MATCH(E52,Valeurs!$A$2:$A$40,0))*INDEX(Valeurs!$E$2:$E$40,MATCH(E52,Valeurs!$A$2:$A$40,0)) -> 0 | J52: 1
A53: 46297 | B53: Petit-déjeuner | C53: Smoothie + œuf (Nicolas) / œufs, jambon, pain, pomme (Aurélie) | D53: Aurélie | E53: Tomates | F53: =Menu!E34 -> 80 | G53: g | H53: =F53/INDEX(Valeurs!$B$2:$B$40,MATCH(E53,Valeurs!$A$2:$A$40,0))*INDEX(Valeurs!$D$2:$D$40,MATCH(E53,Valeurs!$A$2:$A$40,0)) -> 14.4 | I53: =F53/INDEX(Valeurs!$B$2:$B$40,MATCH(E53,Valeurs!$A$2:$A$40,0))*INDEX(Valeurs!$E$2:$E$40,MATCH(E53,Valeurs!$A$2:$A$40,0)) -> 0.72 | J53: 1
A54: 46297 | B54: Petit-déjeuner | C54: Smoothie + œuf (Nicolas) / œufs, jambon, pain, pomme (Aurélie) | D54: Nicolas | E54: Pain complet | F54: =Menu!D35 -> 0 | G54: g | H54: =F54/INDEX(Valeurs!$B$2:$B$40,MATCH(E54,Valeurs!$A$2:$A$40,0))*INDEX(Valeurs!$D$2:$D$40,MATCH(E54,Valeurs!$A$2:$A$40,0)) -> 0 | I54: =F54/INDEX(Valeurs!$B$2:$B$40,MATCH(E54,Valeurs!$A$2:$A$40,0))*INDEX(Valeurs!$E$2:$E$40,MATCH(E54,Valeurs!$A$2:$A$40,0)) -> 0 | J54: 1
A55: 46297 | B55: Petit-déjeuner | C55: Smoothie + œuf (Nicolas) / œufs, jambon, pain, pomme (Aurélie) | D55: Aurélie | E55: Pain complet | F55: =Menu!E35 -> 40 | G55: g | H55: =F55/INDEX(Valeurs!$B$2:$B$40,MATCH(E55,Valeurs!$A$2:$A$40,0))*INDEX(Valeurs!$D$2:$D$40,MATCH(E55,Valeurs!$A$2:$A$40,0)) -> 96 | I55: =F55/INDEX(Valeurs!$B$2:$B$40,MATCH(E55,Valeurs!$A$2:$A$40,0))*INDEX(Valeurs!$E$2:$E$40,MATCH(E55,Valeurs!$A$2:$A$40,0)) -> 3.6 | J55: 1
A56: 46297 | B56: Petit-déjeuner | C56: Smoothie + œuf (Nicolas) / œufs, jambon, pain, pomme (Aurélie) | D56: Nicolas | E56: Pommes | F56: =Menu!D36 -> 0 | G56: g | H56: =F56/INDEX(Valeurs!$B$2:$B$40,MATCH(E56,Valeurs!$A$2:$A$40,0))*INDEX(Valeurs!$D$2:$D$40,MATCH(E56,Valeurs!$A$2:$A$40,0)) -> 0 | I56: =F56/INDEX(Valeurs!$B$2:$B$40,MATCH(E56,Valeurs!$A$2:$A$40,0))*INDEX(Valeurs!$E$2:$E$40,MATCH(E56,Valeurs!$A$2:$A$40,0)) -> 0 | J56: 1
A57: 46297 | B57: Petit-déjeuner | C57: Smoothie + œuf (Nicolas) / œufs, jambon, pain, pomme (Aurélie) | D57: Aurélie | E57: Pommes | F57: =Menu!E36 -> 150 | G57: g | H57: =F57/INDEX(Valeurs!$B$2:$B$40,MATCH(E57,Valeurs!$A$2:$A$40,0))*INDEX(Valeurs!$D$2:$D$40,MATCH(E57,Valeurs!$A$2:$A$40,0)) -> 78 | I57: =F57/INDEX(Valeurs!$B$2:$B$40,MATCH(E57,Valeurs!$A$2:$A$40,0))*INDEX(Valeurs!$E$2:$E$40,MATCH(E57,Valeurs!$A$2:$A$40,0)) -> 0.45 | J57: 1
A58: 46297 | B58: Déjeuner | C58: Carry poulet-lentilles, riz, carottes râpées | D58: Nicolas | E58: Poulet | F58: =Menu!D37 -> 100 | G58: g | H58: =F58/INDEX(Valeurs!$B$2:$B$40,MATCH(E58,Valeurs!$A$2:$A$40,0))*INDEX(Valeurs!$D$2:$D$40,MATCH(E58,Valeurs!$A$2:$A$40,0)) -> 115 | I58: =F58/INDEX(Valeurs!$B$2:$B$40,MATCH(E58,Valeurs!$A$2:$A$40,0))*INDEX(Valeurs!$E$2:$E$40,MATCH(E58,Valeurs!$A$2:$A$40,0)) -> 23 | J58: 1
A59: 46297 | B59: Déjeuner | C59: Carry poulet-lentilles, riz, carottes râpées | D59: Aurélie | E59: Poulet | F59: =Menu!E37 -> 80 | G59: g | H59: =F59/INDEX(Valeurs!$B$2:$B$40,MATCH(E59,Valeurs!$A$2:$A$40,0))*INDEX(Valeurs!$D$2:$D$40,MATCH(E59,Valeurs!$A$2:$A$40,0)) -> 92 | I59: =F59/INDEX(Valeurs!$B$2:$B$40,MATCH(E59,Valeurs!$A$2:$A$40,0))*INDEX(Valeurs!$E$2:$E$40,MATCH(E59,Valeurs!$A$2:$A$40,0)) -> 18.4 | J59: 1
A60: 46297 | B60: Déjeuner | C60: Carry poulet-lentilles, riz, carottes râpées | D60: Nicolas | E60: Lentilles (égouttées) | F60: =Menu!D38 -> 140 | G60: g | H60: =F60/INDEX(Valeurs!$B$2:$B$40,MATCH(E60,Valeurs!$A$2:$A$40,0))*INDEX(Valeurs!$D$2:$D$40,MATCH(E60,Valeurs!$A$2:$A$40,0)) -> 140 | I60: =F60/INDEX(Valeurs!$B$2:$B$40,MATCH(E60,Valeurs!$A$2:$A$40,0))*INDEX(Valeurs!$E$2:$E$40,MATCH(E60,Valeurs!$A$2:$A$40,0)) -> 10.5 | J60: 1
A61: 46297 | B61: Déjeuner | C61: Carry poulet-lentilles, riz, carottes râpées | D61: Aurélie | E61: Lentilles (égouttées) | F61: =Menu!E38 -> 120 | G61: g | H61: =F61/INDEX(Valeurs!$B$2:$B$40,MATCH(E61,Valeurs!$A$2:$A$40,0))*INDEX(Valeurs!$D$2:$D$40,MATCH(E61,Valeurs!$A$2:$A$40,0)) -> 120 | I61: =F61/INDEX(Valeurs!$B$2:$B$40,MATCH(E61,Valeurs!$A$2:$A$40,0))*INDEX(Valeurs!$E$2:$E$40,MATCH(E61,Valeurs!$A$2:$A$40,0)) -> 9 | J61: 1
A62: 46297 | B62: Déjeuner | C62: Carry poulet-lentilles, riz, carottes râpées | D62: Nicolas | E62: Riz (sec) | F62: =Menu!D39 -> 50 | G62: g | H62: =F62/INDEX(Valeurs!$B$2:$B$40,MATCH(E62,Valeurs!$A$2:$A$40,0))*INDEX(Valeurs!$D$2:$D$40,MATCH(E62,Valeurs!$A$2:$A$40,0)) -> 177.5 | I62: =F62/INDEX(Valeurs!$B$2:$B$40,MATCH(E62,Valeurs!$A$2:$A$40,0))*INDEX(Valeurs!$E$2:$E$40,MATCH(E62,Valeurs!$A$2:$A$40,0)) -> 3.5 | J62: 1
A63: 46297 | B63: Déjeuner | C63: Carry poulet-lentilles, riz, carottes râpées | D63: Aurélie | E63: Riz (sec) | F63: =Menu!E39 -> 20 | G63: g | H63: =F63/INDEX(Valeurs!$B$2:$B$40,MATCH(E63,Valeurs!$A$2:$A$40,0))*INDEX(Valeurs!$D$2:$D$40,MATCH(E63,Valeurs!$A$2:$A$40,0)) -> 71 | I63: =F63/INDEX(Valeurs!$B$2:$B$40,MATCH(E63,Valeurs!$A$2:$A$40,0))*INDEX(Valeurs!$E$2:$E$40,MATCH(E63,Valeurs!$A$2:$A$40,0)) -> 1.4 | J63: 1
A64: 46297 | B64: Déjeuner | C64: Carry poulet-lentilles, riz, carottes râpées | D64: Nicolas | E64: Tomates | F64: =Menu!D40 -> 120 | G64: g | H64: =F64/INDEX(Valeurs!$B$2:$B$40,MATCH(E64,Valeurs!$A$2:$A$40,0))*INDEX(Valeurs!$D$2:$D$40,MATCH(E64,Valeurs!$A$2:$A$40,0)) -> 21.6 | I64: =F64/INDEX(Valeurs!$B$2:$B$40,MATCH(E64,Valeurs!$A$2:$A$40,0))*INDEX(Valeurs!$E$2:$E$40,MATCH(E64,Valeurs!$A$2:$A$40,0)) -> 1.08 | J64: 1
A65: 46297 | B65: Déjeuner | C65: Carry poulet-lentilles, riz, carottes râpées | D65: Aurélie | E65: Tomates | F65: =Menu!E40 -> 150 | G65: g | H65: =F65/INDEX(Valeurs!$B$2:$B$40,MATCH(E65,Valeurs!$A$2:$A$40,0))*INDEX(Valeurs!$D$2:$D$40,MATCH(E65,Valeurs!$A$2:$A$40,0)) -> 27 | I65: =F65/INDEX(Valeurs!$B$2:$B$40,MATCH(E65,Valeurs!$A$2:$A$40,0))*INDEX(Valeurs!$E$2:$E$40,MATCH(E65,Valeurs!$A$2:$A$40,0)) -> 1.35 | J65: 1
A66: 46297 | B66: Déjeuner | C66: Carry poulet-lentilles, riz, carottes râpées | D66: Nicolas | E66: Oignons | F66: =Menu!D41 -> 40 | G66: g | H66: =F66/INDEX(Valeurs!$B$2:$B$40,MATCH(E66,Valeurs!$A$2:$A$40,0))*INDEX(Valeurs!$D$2:$D$40,MATCH(E66,Valeurs!$A$2:$A$40,0)) -> 16 | I66: =F66/INDEX(Valeurs!$B$2:$B$40,MATCH(E66,Valeurs!$A$2:$A$40,0))*INDEX(Valeurs!$E$2:$E$40,MATCH(E66,Valeurs!$A$2:$A$40,0)) -> 0.44 | J66: 1
A67: 46297 | B67: Déjeuner | C67: Carry poulet-lentilles, riz, carottes râpées | D67: Aurélie | E67: Oignons | F67: =Menu!E41 -> 40 | G67: g | H67: =F67/INDEX(Valeurs!$B$2:$B$40,MATCH(E67,Valeurs!$A$2:$A$40,0))*INDEX(Valeurs!$D$2:$D$40,MATCH(E67,Valeurs!$A$2:$A$40,0)) -> 16 | I67: =F67/INDEX(Valeurs!$B$2:$B$40,MATCH(E67,Valeurs!$A$2:$A$40,0))*INDEX(Valeurs!$E$2:$E$40,MATCH(E67,Valeurs!$A$2:$A$40,0)) -> 0.44 | J67: 1
A68: 46297 | B68: Déjeuner | C68: Carry poulet-lentilles, riz, carottes râpées | D68: Nicolas | E68: Carottes | F68: =Menu!D42 -> 80 | G68: g | H68: =F68/INDEX(Valeurs!$B$2:$B$40,MATCH(E68,Valeurs!$A$2:$A$40,0))*INDEX(Valeurs!$D$2:$D$40,MATCH(E68,Valeurs!$A$2:$A$40,0)) -> 32.8 | I68: =F68/INDEX(Valeurs!$B$2:$B$40,MATCH(E68,Valeurs!$A$2:$A$40,0))*INDEX(Valeurs!$E$2:$E$40,MATCH(E68,Valeurs!$A$2:$A$40,0)) -> 0.72 | J68: 1
A69: 46297 | B69: Déjeuner | C69: Carry poulet-lentilles, riz, carottes râpées | D69: Aurélie | E69: Carottes | F69: =Menu!E42 -> 100 | G69: g | H69: =F69/INDEX(Valeurs!$B$2:$B$40,MATCH(E69,Valeurs!$A$2:$A$40,0))*INDEX(Valeurs!$D$2:$D$40,MATCH(E69,Valeurs!$A$2:$A$40,0)) -> 41 | I69: =F69/INDEX(Valeurs!$B$2:$B$40,MATCH(E69,Valeurs!$A$2:$A$40,0))*INDEX(Valeurs!$E$2:$E$40,MATCH(E69,Valeurs!$A$2:$A$40,0)) -> 0.9 | J69: 1
A70: 46297 | B70: Déjeuner | C70: Carry poulet-lentilles, riz, carottes râpées | D70: Nicolas | E70: Huile | F70: =Menu!D43 -> 10 | G70: g | H70: =F70/INDEX(Valeurs!$B$2:$B$40,MATCH(E70,Valeurs!$A$2:$A$40,0))*INDEX(Valeurs!$D$2:$D$40,MATCH(E70,Valeurs!$A$2:$A$40,0)) -> 90 | I70: =F70/INDEX(Valeurs!$B$2:$B$40,MATCH(E70,Valeurs!$A$2:$A$40,0))*INDEX(Valeurs!$E$2:$E$40,MATCH(E70,Valeurs!$A$2:$A$40,0)) -> 0 | J70: 1
A71: 46297 | B71: Déjeuner | C71: Carry poulet-lentilles, riz, carottes râpées | D71: Aurélie | E71: Huile | F71: =Menu!E43 -> 7 | G71: g | H71: =F71/INDEX(Valeurs!$B$2:$B$40,MATCH(E71,Valeurs!$A$2:$A$40,0))*INDEX(Valeurs!$D$2:$D$40,MATCH(E71,Valeurs!$A$2:$A$40,0)) -> 63 | I71: =F71/INDEX(Valeurs!$B$2:$B$40,MATCH(E71,Valeurs!$A$2:$A$40,0))*INDEX(Valeurs!$E$2:$E$40,MATCH(E71,Valeurs!$A$2:$A$40,0)) -> 0 | J71: 1
A72: 46297 | B72: Dîner | C72: Omelette paysanne (pommes de terre, courgettes) + salade-tomate | D72: Nicolas | E72: Œufs | F72: =Menu!D44 -> 3 | G72: unité | H72: =F72/INDEX(Valeurs!$B$2:$B$40,MATCH(E72,Valeurs!$A$2:$A$40,0))*INDEX(Valeurs!$D$2:$D$40,MATCH(E72,Valeurs!$A$2:$A$40,0)) -> 261 | I72: =F72/INDEX(Valeurs!$B$2:$B$40,MATCH(E72,Valeurs!$A$2:$A$40,0))*INDEX(Valeurs!$E$2:$E$40,MATCH(E72,Valeurs!$A$2:$A$40,0)) -> 22.5 | J72: 1
A73: 46297 | B73: Dîner | C73: Omelette paysanne (pommes de terre, courgettes) + salade-tomate | D73: Aurélie | E73: Œufs | F73: =Menu!E44 -> 2 | G73: unité | H73: =F73/INDEX(Valeurs!$B$2:$B$40,MATCH(E73,Valeurs!$A$2:$A$40,0))*INDEX(Valeurs!$D$2:$D$40,MATCH(E73,Valeurs!$A$2:$A$40,0)) -> 174 | I73: =F73/INDEX(Valeurs!$B$2:$B$40,MATCH(E73,Valeurs!$A$2:$A$40,0))*INDEX(Valeurs!$E$2:$E$40,MATCH(E73,Valeurs!$A$2:$A$40,0)) -> 15 | J73: 1
A74: 46297 | B74: Dîner | C74: Omelette paysanne (pommes de terre, courgettes) + salade-tomate | D74: Nicolas | E74: Pommes de terre | F74: =Menu!D45 -> 300 | G74: g | H74: =F74/INDEX(Valeurs!$B$2:$B$40,MATCH(E74,Valeurs!$A$2:$A$40,0))*INDEX(Valeurs!$D$2:$D$40,MATCH(E74,Valeurs!$A$2:$A$40,0)) -> 240 | I74: =F74/INDEX(Valeurs!$B$2:$B$40,MATCH(E74,Valeurs!$A$2:$A$40,0))*INDEX(Valeurs!$E$2:$E$40,MATCH(E74,Valeurs!$A$2:$A$40,0)) -> 6 | J74: 1
A75: 46297 | B75: Dîner | C75: Omelette paysanne (pommes de terre, courgettes) + salade-tomate | D75: Aurélie | E75: Pommes de terre | F75: =Menu!E45 -> 110 | G75: g | H75: =F75/INDEX(Valeurs!$B$2:$B$40,MATCH(E75,Valeurs!$A$2:$A$40,0))*INDEX(Valeurs!$D$2:$D$40,MATCH(E75,Valeurs!$A$2:$A$40,0)) -> 88 | I75: =F75/INDEX(Valeurs!$B$2:$B$40,MATCH(E75,Valeurs!$A$2:$A$40,0))*INDEX(Valeurs!$E$2:$E$40,MATCH(E75,Valeurs!$A$2:$A$40,0)) -> 2.2 | J75: 1
A76: 46297 | B76: Dîner | C76: Omelette paysanne (pommes de terre, courgettes) + salade-tomate | D76: Nicolas | E76: Courgettes | F76: =Menu!D46 -> 150 | G76: g | H76: =F76/INDEX(Valeurs!$B$2:$B$40,MATCH(E76,Valeurs!$A$2:$A$40,0))*INDEX(Valeurs!$D$2:$D$40,MATCH(E76,Valeurs!$A$2:$A$40,0)) -> 25.5 | I76: =F76/INDEX(Valeurs!$B$2:$B$40,MATCH(E76,Valeurs!$A$2:$A$40,0))*INDEX(Valeurs!$E$2:$E$40,MATCH(E76,Valeurs!$A$2:$A$40,0)) -> 1.8 | J76: 1
A77: 46297 | B77: Dîner | C77: Omelette paysanne (pommes de terre, courgettes) + salade-tomate | D77: Aurélie | E77: Courgettes | F77: =Menu!E46 -> 170 | G77: g | H77: =F77/INDEX(Valeurs!$B$2:$B$40,MATCH(E77,Valeurs!$A$2:$A$40,0))*INDEX(Valeurs!$D$2:$D$40,MATCH(E77,Valeurs!$A$2:$A$40,0)) -> 28.9 | I77: =F77/INDEX(Valeurs!$B$2:$B$40,MATCH(E77,Valeurs!$A$2:$A$40,0))*INDEX(Valeurs!$E$2:$E$40,MATCH(E77,Valeurs!$A$2:$A$40,0)) -> 2.04 | J77: 1
A78: 46297 | B78: Dîner | C78: Omelette paysanne (pommes de terre, courgettes) + salade-tomate | D78: Nicolas | E78: Tomates | F78: =Menu!D47 -> 100 | G78: g | H78: =F78/INDEX(Valeurs!$B$2:$B$40,MATCH(E78,Valeurs!$A$2:$A$40,0))*INDEX(Valeurs!$D$2:$D$40,MATCH(E78,Valeurs!$A$2:$A$40,0)) -> 18 | I78: =F78/INDEX(Valeurs!$B$2:$B$40,MATCH(E78,Valeurs!$A$2:$A$40,0))*INDEX(Valeurs!$E$2:$E$40,MATCH(E78,Valeurs!$A$2:$A$40,0)) -> 0.9 | J78: 1
A79: 46297 | B79: Dîner | C79: Omelette paysanne (pommes de terre, courgettes) + salade-tomate | D79: Aurélie | E79: Tomates | F79: =Menu!E47 -> 130 | G79: g | H79: =F79/INDEX(Valeurs!$B$2:$B$40,MATCH(E79,Valeurs!$A$2:$A$40,0))*INDEX(Valeurs!$D$2:$D$40,MATCH(E79,Valeurs!$A$2:$A$40,0)) -> 23.4 | I79: =F79/INDEX(Valeurs!$B$2:$B$40,MATCH(E79,Valeurs!$A$2:$A$40,0))*INDEX(Valeurs!$E$2:$E$40,MATCH(E79,Valeurs!$A$2:$A$40,0)) -> 1.17 | J79: 1
A80: 46297 | B80: Dîner | C80: Omelette paysanne (pommes de terre, courgettes) + salade-tomate | D80: Nicolas | E80: Salade | F80: =Menu!D48 -> 40 | G80: g | H80: =F80/INDEX(Valeurs!$B$2:$B$40,MATCH(E80,Valeurs!$A$2:$A$40,0))*INDEX(Valeurs!$D$2:$D$40,MATCH(E80,Valeurs!$A$2:$A$40,0)) -> 6 | I80: =F80/INDEX(Valeurs!$B$2:$B$40,MATCH(E80,Valeurs!$A$2:$A$40,0))*INDEX(Valeurs!$E$2:$E$40,MATCH(E80,Valeurs!$A$2:$A$40,0)) -> 0.56 | J80: 1
A81: 46297 | B81: Dîner | C81: Omelette paysanne (pommes de terre, courgettes) + salade-tomate | D81: Aurélie | E81: Salade | F81: =Menu!E48 -> 60 | G81: g | H81: =F81/INDEX(Valeurs!$B$2:$B$40,MATCH(E81,Valeurs!$A$2:$A$40,0))*INDEX(Valeurs!$D$2:$D$40,MATCH(E81,Valeurs!$A$2:$A$40,0)) -> 9 | I81: =F81/INDEX(Valeurs!$B$2:$B$40,MATCH(E81,Valeurs!$A$2:$A$40,0))*INDEX(Valeurs!$E$2:$E$40,MATCH(E81,Valeurs!$A$2:$A$40,0)) -> 0.84 | J81: 1
A82: 46297 | B82: Dîner | C82: Omelette paysanne (pommes de terre, courgettes) + salade-tomate | D82: Nicolas | E82: Oignons | F82: =Menu!D49 -> 20 | G82: g | H82: =F82/INDEX(Valeurs!$B$2:$B$40,MATCH(E82,Valeurs!$A$2:$A$40,0))*INDEX(Valeurs!$D$2:$D$40,MATCH(E82,Valeurs!$A$2:$A$40,0)) -> 8 | I82: =F82/INDEX(Valeurs!$B$2:$B$40,MATCH(E82,Valeurs!$A$2:$A$40,0))*INDEX(Valeurs!$E$2:$E$40,MATCH(E82,Valeurs!$A$2:$A$40,0)) -> 0.22 | J82: 1
A83: 46297 | B83: Dîner | C83: Omelette paysanne (pommes de terre, courgettes) + salade-tomate | D83: Aurélie | E83: Oignons | F83: =Menu!E49 -> 20 | G83: g | H83: =F83/INDEX(Valeurs!$B$2:$B$40,MATCH(E83,Valeurs!$A$2:$A$40,0))*INDEX(Valeurs!$D$2:$D$40,MATCH(E83,Valeurs!$A$2:$A$40,0)) -> 8 | I83: =F83/INDEX(Valeurs!$B$2:$B$40,MATCH(E83,Valeurs!$A$2:$A$40,0))*INDEX(Valeurs!$E$2:$E$40,MATCH(E83,Valeurs!$A$2:$A$40,0)) -> 0.22 | J83: 1
A84: 46297 | B84: Dîner | C84: Omelette paysanne (pommes de terre, courgettes) + salade-tomate | D84: Nicolas | E84: Huile | F84: =Menu!D50 -> 8 | G84: g | H84: =F84/INDEX(Valeurs!$B$2:$B$40,MATCH(E84,Valeurs!$A$2:$A$40,0))*INDEX(Valeurs!$D$2:$D$40,MATCH(E84,Valeurs!$A$2:$A$40,0)) -> 72 | I84: =F84/INDEX(Valeurs!$B$2:$B$40,MATCH(E84,Valeurs!$A$2:$A$40,0))*INDEX(Valeurs!$E$2:$E$40,MATCH(E84,Valeurs!$A$2:$A$40,0)) -> 0 | J84: 1
A85: 46297 | B85: Dîner | C85: Omelette paysanne (pommes de terre, courgettes) + salade-tomate | D85: Aurélie | E85: Huile | F85: =Menu!E50 -> 6 | G85: g | H85: =F85/INDEX(Valeurs!$B$2:$B$40,MATCH(E85,Valeurs!$A$2:$A$40,0))*INDEX(Valeurs!$D$2:$D$40,MATCH(E85,Valeurs!$A$2:$A$40,0)) -> 54 | I85: =F85/INDEX(Valeurs!$B$2:$B$40,MATCH(E85,Valeurs!$A$2:$A$40,0))*INDEX(Valeurs!$E$2:$E$40,MATCH(E85,Valeurs!$A$2:$A$40,0)) -> 0 | J85: 1
A86: 46297 | B86: Dessert | C86: Ananas | D86: Nicolas | E86: Ananas | F86: =Menu!D51 -> 110 | G86: g | H86: =F86/INDEX(Valeurs!$B$2:$B$40,MATCH(E86,Valeurs!$A$2:$A$40,0))*INDEX(Valeurs!$D$2:$D$40,MATCH(E86,Valeurs!$A$2:$A$40,0)) -> 55 | I86: =F86/INDEX(Valeurs!$B$2:$B$40,MATCH(E86,Valeurs!$A$2:$A$40,0))*INDEX(Valeurs!$E$2:$E$40,MATCH(E86,Valeurs!$A$2:$A$40,0)) -> 0.55 | J86: 1
A87: 46297 | B87: Dessert | C87: Ananas | D87: Aurélie | E87: Ananas | F87: =Menu!E51 -> 90 | G87: g | H87: =F87/INDEX(Valeurs!$B$2:$B$40,MATCH(E87,Valeurs!$A$2:$A$40,0))*INDEX(Valeurs!$D$2:$D$40,MATCH(E87,Valeurs!$A$2:$A$40,0)) -> 45 | I87: =F87/INDEX(Valeurs!$B$2:$B$40,MATCH(E87,Valeurs!$A$2:$A$40,0))*INDEX(Valeurs!$E$2:$E$40,MATCH(E87,Valeurs!$A$2:$A$40,0)) -> 0.45 | J87: 1
A88: 46298 | B88: Petit-déjeuner | C88: Smoothie + œuf (Nicolas) / œufs, jambon, pain, pomme (Aurélie) | D88: Nicolas | E88: Lait | F88: =Menu!D54 -> 250 | G88: ml | H88: =F88/INDEX(Valeurs!$B$2:$B$40,MATCH(E88,Valeurs!$A$2:$A$40,0))*INDEX(Valeurs!$D$2:$D$40,MATCH(E88,Valeurs!$A$2:$A$40,0)) -> 115 | I88: =F88/INDEX(Valeurs!$B$2:$B$40,MATCH(E88,Valeurs!$A$2:$A$40,0))*INDEX(Valeurs!$E$2:$E$40,MATCH(E88,Valeurs!$A$2:$A$40,0)) -> 8.25 | J88: 1
A89: 46298 | B89: Petit-déjeuner | C89: Smoothie + œuf (Nicolas) / œufs, jambon, pain, pomme (Aurélie) | D89: Aurélie | E89: Lait | F89: =Menu!E54 -> 0 | G89: ml | H89: =F89/INDEX(Valeurs!$B$2:$B$40,MATCH(E89,Valeurs!$A$2:$A$40,0))*INDEX(Valeurs!$D$2:$D$40,MATCH(E89,Valeurs!$A$2:$A$40,0)) -> 0 | I89: =F89/INDEX(Valeurs!$B$2:$B$40,MATCH(E89,Valeurs!$A$2:$A$40,0))*INDEX(Valeurs!$E$2:$E$40,MATCH(E89,Valeurs!$A$2:$A$40,0)) -> 0 | J89: 1
A90: 46298 | B90: Petit-déjeuner | C90: Smoothie + œuf (Nicolas) / œufs, jambon, pain, pomme (Aurélie) | D90: Nicolas | E90: Bananes | F90: =Menu!D55 -> 100 | G90: g | H90: =F90/INDEX(Valeurs!$B$2:$B$40,MATCH(E90,Valeurs!$A$2:$A$40,0))*INDEX(Valeurs!$D$2:$D$40,MATCH(E90,Valeurs!$A$2:$A$40,0)) -> 90 | I90: =F90/INDEX(Valeurs!$B$2:$B$40,MATCH(E90,Valeurs!$A$2:$A$40,0))*INDEX(Valeurs!$E$2:$E$40,MATCH(E90,Valeurs!$A$2:$A$40,0)) -> 1.1 | J90: 1
A91: 46298 | B91: Petit-déjeuner | C91: Smoothie + œuf (Nicolas) / œufs, jambon, pain, pomme (Aurélie) | D91: Aurélie | E91: Bananes | F91: =Menu!E55 -> 0 | G91: g | H91: =F91/INDEX(Valeurs!$B$2:$B$40,MATCH(E91,Valeurs!$A$2:$A$40,0))*INDEX(Valeurs!$D$2:$D$40,MATCH(E91,Valeurs!$A$2:$A$40,0)) -> 0 | I91: =F91/INDEX(Valeurs!$B$2:$B$40,MATCH(E91,Valeurs!$A$2:$A$40,0))*INDEX(Valeurs!$E$2:$E$40,MATCH(E91,Valeurs!$A$2:$A$40,0)) -> 0 | J91: 1
A92: 46298 | B92: Petit-déjeuner | C92: Smoothie + œuf (Nicolas) / œufs, jambon, pain, pomme (Aurélie) | D92: Nicolas | E92: Flocons d'avoine | F92: =Menu!D56 -> 65 | G92: g | H92: =F92/INDEX(Valeurs!$B$2:$B$40,MATCH(E92,Valeurs!$A$2:$A$40,0))*INDEX(Valeurs!$D$2:$D$40,MATCH(E92,Valeurs!$A$2:$A$40,0)) -> 241.8 | I92: =F92/INDEX(Valeurs!$B$2:$B$40,MATCH(E92,Valeurs!$A$2:$A$40,0))*INDEX(Valeurs!$E$2:$E$40,MATCH(E92,Valeurs!$A$2:$A$40,0)) -> 8.775 | J92: 1
A93: 46298 | B93: Petit-déjeuner | C93: Smoothie + œuf (Nicolas) / œufs, jambon, pain, pomme (Aurélie) | D93: Aurélie | E93: Flocons d'avoine | F93: =Menu!E56 -> 0 | G93: g | H93: =F93/INDEX(Valeurs!$B$2:$B$40,MATCH(E93,Valeurs!$A$2:$A$40,0))*INDEX(Valeurs!$D$2:$D$40,MATCH(E93,Valeurs!$A$2:$A$40,0)) -> 0 | I93: =F93/INDEX(Valeurs!$B$2:$B$40,MATCH(E93,Valeurs!$A$2:$A$40,0))*INDEX(Valeurs!$E$2:$E$40,MATCH(E93,Valeurs!$A$2:$A$40,0)) -> 0 | J93: 1
A94: 46298 | B94: Petit-déjeuner | C94: Smoothie + œuf (Nicolas) / œufs, jambon, pain, pomme (Aurélie) | D94: Nicolas | E94: Œufs | F94: =Menu!D57 -> 1 | G94: unité | H94: =F94/INDEX(Valeurs!$B$2:$B$40,MATCH(E94,Valeurs!$A$2:$A$40,0))*INDEX(Valeurs!$D$2:$D$40,MATCH(E94,Valeurs!$A$2:$A$40,0)) -> 87 | I94: =F94/INDEX(Valeurs!$B$2:$B$40,MATCH(E94,Valeurs!$A$2:$A$40,0))*INDEX(Valeurs!$E$2:$E$40,MATCH(E94,Valeurs!$A$2:$A$40,0)) -> 7.5 | J94: 1
A95: 46298 | B95: Petit-déjeuner | C95: Smoothie + œuf (Nicolas) / œufs, jambon, pain, pomme (Aurélie) | D95: Aurélie | E95: Œufs | F95: =Menu!E57 -> 2 | G95: unité | H95: =F95/INDEX(Valeurs!$B$2:$B$40,MATCH(E95,Valeurs!$A$2:$A$40,0))*INDEX(Valeurs!$D$2:$D$40,MATCH(E95,Valeurs!$A$2:$A$40,0)) -> 174 | I95: =F95/INDEX(Valeurs!$B$2:$B$40,MATCH(E95,Valeurs!$A$2:$A$40,0))*INDEX(Valeurs!$E$2:$E$40,MATCH(E95,Valeurs!$A$2:$A$40,0)) -> 15 | J95: 1
A96: 46298 | B96: Petit-déjeuner | C96: Smoothie + œuf (Nicolas) / œufs, jambon, pain, pomme (Aurélie) | D96: Nicolas | E96: Jambon | F96: =Menu!D58 -> 0 | G96: g | H96: =F96/INDEX(Valeurs!$B$2:$B$40,MATCH(E96,Valeurs!$A$2:$A$40,0))*INDEX(Valeurs!$D$2:$D$40,MATCH(E96,Valeurs!$A$2:$A$40,0)) -> 0 | I96: =F96/INDEX(Valeurs!$B$2:$B$40,MATCH(E96,Valeurs!$A$2:$A$40,0))*INDEX(Valeurs!$E$2:$E$40,MATCH(E96,Valeurs!$A$2:$A$40,0)) -> 0 | J96: 1
A97: 46298 | B97: Petit-déjeuner | C97: Smoothie + œuf (Nicolas) / œufs, jambon, pain, pomme (Aurélie) | D97: Aurélie | E97: Jambon | F97: =Menu!E58 -> 30 | G97: g | H97: =F97/INDEX(Valeurs!$B$2:$B$40,MATCH(E97,Valeurs!$A$2:$A$40,0))*INDEX(Valeurs!$D$2:$D$40,MATCH(E97,Valeurs!$A$2:$A$40,0)) -> 33 | I97: =F97/INDEX(Valeurs!$B$2:$B$40,MATCH(E97,Valeurs!$A$2:$A$40,0))*INDEX(Valeurs!$E$2:$E$40,MATCH(E97,Valeurs!$A$2:$A$40,0)) -> 6 | J97: 1
A98: 46298 | B98: Petit-déjeuner | C98: Smoothie + œuf (Nicolas) / œufs, jambon, pain, pomme (Aurélie) | D98: Nicolas | E98: Tomates | F98: =Menu!D59 -> 0 | G98: g | H98: =F98/INDEX(Valeurs!$B$2:$B$40,MATCH(E98,Valeurs!$A$2:$A$40,0))*INDEX(Valeurs!$D$2:$D$40,MATCH(E98,Valeurs!$A$2:$A$40,0)) -> 0 | I98: =F98/INDEX(Valeurs!$B$2:$B$40,MATCH(E98,Valeurs!$A$2:$A$40,0))*INDEX(Valeurs!$E$2:$E$40,MATCH(E98,Valeurs!$A$2:$A$40,0)) -> 0 | J98: 1
A99: 46298 | B99: Petit-déjeuner | C99: Smoothie + œuf (Nicolas) / œufs, jambon, pain, pomme (Aurélie) | D99: Aurélie | E99: Tomates | F99: =Menu!E59 -> 80 | G99: g | H99: =F99/INDEX(Valeurs!$B$2:$B$40,MATCH(E99,Valeurs!$A$2:$A$40,0))*INDEX(Valeurs!$D$2:$D$40,MATCH(E99,Valeurs!$A$2:$A$40,0)) -> 14.4 | I99: =F99/INDEX(Valeurs!$B$2:$B$40,MATCH(E99,Valeurs!$A$2:$A$40,0))*INDEX(Valeurs!$E$2:$E$40,MATCH(E99,Valeurs!$A$2:$A$40,0)) -> 0.72 | J99: 1
A100: 46298 | B100: Petit-déjeuner | C100: Smoothie + œuf (Nicolas) / œufs, jambon, pain, pomme (Aurélie) | D100: Nicolas | E100: Pain complet | F100: =Menu!D60 -> 0 | G100: g | H100: =F100/INDEX(Valeurs!$B$2:$B$40,MATCH(E100,Valeurs!$A$2:$A$40,0))*INDEX(Valeurs!$D$2:$D$40,MATCH(E100,Valeurs!$A$2:$A$40,0)) -> 0 | I100: =F100/INDEX(Valeurs!$B$2:$B$40,MATCH(E100,Valeurs!$A$2:$A$40,0))*INDEX(Valeurs!$E$2:$E$40,MATCH(E100,Valeurs!$A$2:$A$40,0)) -> 0 | J100: 1
...

Sheet Valeurs
A1: Aliment | B1: Base | C1: Unité | D1: kcal par base | E1: Protéines (g) par base
A2: Poulet | B2: 100 | C2: g | D2: 115 | E2: 23
A3: Bœuf | B3: 100 | C3: g | D3: 140 | E3: 21
A4: Lardons | B4: 100 | C4: g | D4: 270 | E4: 15
A5: Jambon | B5: 100 | C5: g | D5: 110 | E5: 20
A6: Poisson blanc | B6: 100 | C6: g | D6: 80 | E6: 17
A7: Œufs | B7: 1 | C7: unité | D7: 87 | E7: 7.5
A8: Lait | B8: 100 | C8: ml | D8: 46 | E8: 3.3
A9: Mozzarella râpée | B9: 100 | C9: g | D9: 280 | E9: 21
A10: Cheddar | B10: 100 | C10: g | D10: 410 | E10: 25
A11: Riz (sec) | B11: 100 | C11: g | D11: 355 | E11: 7
A12: Pâtes (sèches) | B12: 100 | C12: g | D12: 355 | E12: 12.5
A13: Pâtes à lasagnes (sèches) | B13: 100 | C13: g | D13: 355 | E13: 12.5
... A40: Farine | B40: 100 | C40: g | D40: 350 | E40: 10
A42: Valeurs moyennes arrondies (ordre de grandeur des tables de composition type Ciqual/Anses). Viandes, poissons, féculents : poids crus ou secs ; lentilles : égouttées ; œufs, wraps, pains burger : par unité (œuf ≈ 60 g, wrap ≈ 60 g, pain burger ≈ 75 g). Les chiffres en bleu sont modifiables.
